Workbook
Name AllottedFunds: #REF!
Name AllottedFunds: #REF!
Name Areas: [1]Data!$A$1:$A$11
Name ColumnTitle2: [2]!Data[[#Headers],[Item]]
Name Estimators: [1]Data!$D$1:$D$5
Name FundsRemaining: INDEX(#REF!,ROWS(#REF!),1)
Name FundsRemaining: INDEX(#REF!,ROWS(#REF!),1)
Name FundsRemainingLabel: #REF!
Name FundsRemainingLabel: #REF!
Name FundsUsed: #REF!
Name FundsUsed: #REF!
Name FundsUsedLabel: #REF!
Name FundsUsedLabel: #REF!
Name RowTitleRegion1..C11: #REF!
Name RowTitleRegion1..C11: #REF!
Name Title1: #REF!
Name Title1: #REF!

Sheet Summary
B2: CLIENT
B3: 41 Heritage Park
B4: Presold
B6: Hard coded values
B7: sq.ft. per m2
B9: SECTION 1: PROPERTY DETAILS
B10: Plan | C10: # | D10: 2310771
B11: Block | C11: # | D11: 53
B12: Lot | C12: # | D12: 12
B13: Link to Map
B14: Neighbourhood | D14: Cochrane
B15: Price Range in Neighbourhood | C15: $
B16: Year Built | C16: # | D16: 2026
B18: Site Area | C18: m2 | D18: 342
B19: Site Area | C19: sq. ft. | D19: =D18*10.7639 -> 3681.2538
B20: Floor area above grade | C20: sq. ft. | D20: 2338
B22: Tax-Assessed Value (Land) | C22: $ | D22: 203700
B23: Appraised Land Value | C23: $
B24: Land Cost | C24: $ | D24: =240000 -> 240000
B26: Land Internal Value | C26: $ | D26: ='Land UW'!D33 -> 212711.88
B27: Value Per Front Foot | C27: $ pff | D27: =D26/'Land UW'!L3 -> 6276.3388
C28: .
B29: "As Complete" Appraised Value | C29: $
B30: Unit Price - Appraised Value | C30: $ psf | D30: =D29/D20 -> 0
B32: Internal Value | C32: $ | D32: ='Property Comparables'!D65 -> 818300
B33: GST (5%) | D33: =D32-(D32/1.05) -> 38966.667
B34: Internal Value Pre-Tax | D34: =IF(ISBLANK(D32),"",D32-D33) -> 779333.33
B35: Unit Price - Internal Value | C35: $ psf | D35: =IFERROR(D32/D20,"n/a") -> 350
B37: =IF(B4="Presold","Presale Price","List Price") -> Presale Price | C37: $ | D37: 916000
B38: GST (5%) | C38: $ | D38: =D37-(D37/1.05) -> 43619.048
B39: Value Pre-Tax | C39: $ | D39: =IF(ISBLANK(D37),"",D37-D38) -> 872380.95
B40: Unit Price - Presale Price | C40: $ psf | D40: =IFERROR(D37/D20,"n/a") -> 391.78785
B42: Total Construction Costs (Excluding Land) | C42: $ | D42: 505000
B43: Total Construction Costs (With Land) | C43: $ | D43: =D42+D24 -> 745000
B44: Construction Cost | C44: $ psf | D44: =D42/D20 -> 215.99658

Sheet Land UW
B2: Source | C2: Civic Address - If Known | D2: Plan | E2: Legal Block | F2: Legal Lot | G2: Sale Price | H2: Zoning | I2: Sale Date | J2: Frotage (M) | K2: Depth(M) | L2: Frotage (F) | M2: Build Pocket | N2: Depth(F) | O2: Square feet | P2: Cost per ff | Q2: Cost per build pocket | R2: Price per square foot | S2: Notes
B3: Subject | C3: =Summary!B3 -> 41 Heritage Park | D3: =Summary!D10 -> 2310771 | E3: =Summary!D11 -> 53 | F3: =Summary!D12 -> 12 | G3: =Summary!D24 -> 240000 | J3: 10.33 | L3: =J3*3.28084 -> 33.891077 | O3: =Summary!D19 -> 3681.2538 | P3: =G3/L3 -> 7081.5099 | Q3: =G3/M3 -> #DIV/0! | R3: =G3/O3 -> 65.195179
C4: 37 Heritage Park | D4: 2310771 | E4: 53 | F4: 11 | G4: 240000 | J4: 10.33 | L4: =J4*3.28084 -> 33.891077 | O4: =L4*N4 -> 0 | P4: =G4/L4 -> 7081.5099 | Q4: =G4/M4 -> #DIV/0! | R4: =G4/O4 -> #DIV/0!
C5: 97 Heritage Blvd | D5: 2310771 | E5: 51 | F5: 11 | G5: 220000 | I5: 45799 | J5: 10 | L5: =J5*3.28084 -> 32.8084 | O5: =L5*N5 -> 0 | P5: =G5/L5 -> 6705.5998 | Q5: =G5/M5 -> #DIV/0! | R5: =G5/O5 -> #DIV/0!
C6: 101 Heritage Blvd | D6: 2310771 | E6: 51 | F6: 10 | G6: 210000 | I6: 45799 | J6: 10 | L6: =J6*3.28084 -> 32.8084 | O6: =L6*N6 -> 0 | P6: =G6/L6 -> 6400.7998 | Q6: =G6/M6 -> #DIV/0! | R6: =G6/O6 -> #DIV/0! | S6: Brett's Hertiage Hills borrower
C7: 105 Heritage Blvd | D7: 2310771 | E7: 51 | F7: 9 | G7: 210000 | I7: 46037 | J7: 10 | L7: =J7*3.28084 -> 32.8084 | O7: =L7*N7 -> 0 | P7: =G7/L7 -> 6400.7998 | Q7: =G7/M7 -> #DIV/0! | R7: =G7/O7 -> #DIV/0! | S7: Brett's Hertiage Hills borrower
C8: 109 Heritage Blvd | D8: 2310771 | E8: 51 | F8: 8 | G8: 210000 | I8: 45941 | J8: 10 | L8: =J8*3.28084 -> 32.8084 | O8: =L8*N8 -> 0 | P8: =G8/L8 -> 6400.7998 | Q8: =G8/M8 -> #DIV/0! | R8: =G8/O8 -> #DIV/0! | S8: Brett's Hertiage Hills borrower
C9: 129 Heritage Blvd | D9: 2310771 | E9: 51 | F9: 3 | G9: 210000 | I9: 45941 | J9: 10 | L9: =J9*3.28084 -> 32.8084 | O9: =L9*N9 -> 0 | P9: =G9/L9 -> 6400.7998 | Q9: =G9/M9 -> #DIV/0! | R9: =G9/O9 -> #DIV/0! | S9: Brett's Hertiage Hills borrower
C10: 137 Heritage Blvd | D10: 2310771 | E10: 51 | F10: 1 | G10: 210000 | I10: 45799 | J10: 10 | L10: =J10*3.28084 -> 32.8084 | O10: =L10*N10 -> 0 | P10: =G10/L10 -> 6400.7998 | Q10: =G10/M10 -> #DIV/0! | R10: =G10/O10 -> #DIV/0! | S10: Brett's Hertiage Hills borrower
C11: 3 Heritage Link | D11: 2411850 | E11: 7 | F11: 7 | G11: 193000 | I11: 45819 | J11: 12 | L11: =J11*3.28084 -> 39.37008 | O11: =L11*N11 -> 0 | P11: =G11/L11 -> 4902.1998 | Q11: =G11/M11 -> #DIV/0! | R11: =G11/O11 -> #DIV/0! | S11: End lot
C12: 7-23 Heritage Link | D12: 2411850 | E12: 7 | F12: 2-6 | G12: 193000 | I12: 45819 | J12: 10 | L12: =J12*3.28084 -> 32.8084 | O12: =L12*N12 -> 0 | P12: =G12/L12 -> 5882.6398 | Q12: =G12/M12 -> #DIV/0! | R12: =G12/O12 -> #DIV/0! | S12: Bedrock homes bought 5 lots at this price
C13: 8-28 Heritage Link | D13: 2411850 | E13: 3 | F13: 43-48 | G13: 203000 | I13: 46058 | J13: 10 | L13: =J13*3.28084 -> 32.8084 | O13: =L13*N13 -> 0 | P13: =G13/L13 -> 6187.4398 | Q13: =G13/M13 -> #DIV/0! | R13: =G13/O13 -> #DIV/0! | S13: Bedrock homes bought 6 lots at this price
C16: Average | G16: =AVERAGE(G4:G15) -> 209900
C21: Per Sqf | D21: Per FF
B22: Min | C22: =MIN(R4:R16) -> #DIV/0! | D22: =MIN(P4:P16) -> 4902.1998
B23: 25th Percentile | C23: =_xlfn.PERCENTILE.INC(R4:R16,0.25) -> #DIV/0! | D23: =_xlfn.PERCENTILE.INC(P4:P16,0.25) -> 6240.7798
B24: Median | C24: =MEDIAN(R4:R16) -> #DIV/0! | D24: =MEDIAN(P4:P16) -> 6400.7998
B25: Average | C25: =AVERAGE(R4:R16) -> #DIV/0! | D25: =AVERAGE(P4:P16) -> 6276.3388
B26: 75th Percentile | C26: =_xlfn.PERCENTILE.INC(R4:R16,0.75) -> #DIV/0! | D26: =_xlfn.PERCENTILE.INC(P4:P16,0.75) -> 6400.7998
B27: Max | C27: =MAX(R4:R16) -> #DIV/0! | D27: =MAX(P4:P16) -> 7081.5099
B29: SD | C29: =_xlfn.STDEV.P($R$4:$R$16) -> #DIV/0! | D29: =_xlfn.STDEV.P($P$4:$P$16) -> 544.16707
B31: Internal value | C31: =C23 -> #DIV/0! | D31: =D25 -> 6276.3388
B32: Lot Size | C32: =O3 -> 3681.2538 | D32: =L3 -> 33.891077
B33: Lot Internal Value | C33: =C32*C31 -> #DIV/0! | D33: =D31*D32 -> 212711.88

Sheet Property Comparables
B2: =Summary!B2 -> CLIENT
B3: =Summary!B3 -> 41 Heritage Park
G4: Best Comp 1 | H4: Best Comp 2 | P4: Too Small
B5: Comparable Property # | D5: Subject Property | E5: 1 | F5: =E5+1 -> 2 | G5: =F5+1 -> 3 | J5: =K5+1 -> 5 | K5: =G5+1 -> 4
B6: Address | D6: =B3 -> 41 Heritage Park | E6: 53 Heritage Park | F6: 47 Heritage Heath | G6: 116 Heritage Boulveard | H6: 127 Heritage Court | I6: 172 Southborough Common | J6: 20 Quartz Crescent | K6: 8 Vantage Drive | P6: 25 Southborough Square
B7: Data Source | E7: REALTOR | F7: HD | G7: HD | H7: HD | I7: HD | J7: HD | K7: HD | P7: HD
B9: Price | D9: =Summary!D37 -> 916000 | E9: 879000 | F9: 730000 | G9: 840000 | H9: 724900 | I9: 679900 | J9: 850000 | K9: 860000 | P9: 714190
N10: 2338 and 2455
B11: List Price / Sale Price | D11: Sale Price | E11: List Price | F11: Sale Price | G11: Sale Price | H11: Sale Price | I11: Sale Price | J11: Sale Price | K11: Sale Price | P11: Sale Price
B12: Builder | D12: =B2 -> CLIENT | E12: Canbrook Homes | H12: Homes by Fifty Six | I12: Daytona Homes | K12: Green Cedar Homes | O12: Very nice lot | P12: Daytona Homes
B13: Neighbourhood | D13: =Summary!D14 -> Cochrane | E13: Heritage Hills | F13: Heritage Hills | G13: Heritage Hills | H13: Heritage Hills | I13: Southbow Landing | J13: Greystone | K13: Greystone | O13: Very nice lot | P13: Southbow Landing
B14: Unadjusted Unit Price (sq. ft.) | D14: =IFERROR(D9/D17,"n/a") -> 391.78785 | E14: =IFERROR(E9/E17,"n/a") -> 350.1992 | F14: =IFERROR(F9/F17,"n/a") -> 291.41717 | G14: =IFERROR(G9/G17,"n/a") -> 337.07865 | H14: =IFERROR(H9/H17,"n/a") -> 335.2914 | I14: =IFERROR(I9/I17,"n/a") -> 288.33757 | J14: =IFERROR(J9/J17,"n/a") -> 352.40464 | K14: =IFERROR(K9/K17,"n/a") -> 377.68994 | P14: =IFERROR(P9/P17,"n/a") -> 351.64451
B15: Sale Date | F15: 45947 | G15: 45784 | H15: 45978 | I15: 46042 | J15: 45744 | K15: 46014 | P15: 46042
B17: Floor Area Above Grade (sq. ft.) | D17: =Summary!D20 -> 2338 | E17: 2510 | F17: 2505 | G17: 2492 | H17: 2162 | I17: 2358 | J17: 2412 | K17: 2277 | P17: 2031
B18: Site Size (sq. ft.) | D18: =Summary!D19 -> 3681.2538 | F18: 3699 | G18: 3763 | H18: 3799 | I18: 3896 | J18: 4370 | K18: 3926 | P18: 3674
B19: Style | D19: Single Family | E19: Single Family | F19: Single Family | G19: Single Family | H19: Single Family | I19: Single Family | J19: Single Family | K19: Single Family | P19: Single Family
B20: Format | D20: 2 Storey | E20: 2 Storey | F20: 2 Storey | G20: 2 Storey | H20: 2 Storey | I20: 2 Storey | J20: 2 Storey | K20: 2 Storey | P20: 2 Storey
B21: Year Built | D21: =Summary!D16 -> 2026 | E21: 2026 | F21: 2025 | G21: 2025 | H21: 2025 | I21: 2025 | J21: 2018 | K21: 2022 | P21: 2025
B22: Bedrooms | D22: 3 | E22: 4 | F22: 3 | G22: 4 | H22: 3 | I22: 4 | J22: 5 | K22: 3 | N22: Nicer Comps | P22: 4
B23: Bathrooms | D23: 3.5 | E23: 2.5 | F23: 3 | G23: 3.5 | H23: 2.5 | I23: 2 | J23: 5 | K23: 3.5 | N23: 543 Rivercrest View, Cochrane AB - For Sale | HonestDoor | P23: 2
B24: Basement | D24: Legal Suite | E24: Unfinished | F24: Unfinished | G24: Finished | H24: Unfinished | I24: Unfinished | J24: Finished | K24: Finished | N24: 68 Heritage Ridge, Cochrane AB - For Sale | HonestDoor | O24: Very nice lot | P24: Unfinished
B25: Parking | D25: Double Attached | E25: Double Attached | F25: Double Attached | G25: Double Attached | H25: Double Attached | I25: Double Attached | J25: Double Attached | K25: Double Attached | N25: 76 Heritage Ridge, Cochrane AB - For Sale | HonestDoor | O25: Very nice lot | P25: Double Attached
B26: Fireplace | D26: Gas | E26: Gas | F26: Gas | G26: Electric | H26: Yes | I26: Electric | J26: Gas | K26: Electric | P26: Electric
B27: Deck/Balcony | D27: Deck | E27: Deck | F27: Deck | G27: Deck | H27: Deck | I27: Deck | J27: Deck | K27: Deck | P27: Deck
B28: Appliances | D28: Yes | E28: Yes | F28: Yes | G28: Yes | H28: Yes | I28: No | J28: Yes | K28: Yes | P28: No
B29: Notes | D29: Legal Suite with fire place, walkout lot. Main floor is an extremely odd layout. I cant see access to the garage from the house. | F29: Does not have the open to above ceilings | G29: Does not have the open to above ceilings. Legal suite | H29: Backs Park like subject | I29: Nice home but faily basic | J29: Backs onto walking path. Greystone | K29: Former Green Cedar Showhome. Closing Feb 20.
B30: Appraised/ List Price | D30: =D9 -> 916000 | E30: =E9 -> 879000 | F30: =F9 -> 730000 | G30: =G9 -> 840000 | H30: =H9 -> 724900 | I30: =I9 -> 679900 | J30: =J9 -> 850000 | K30: =K9 -> 860000 | P30: =P9 -> 714190
B31: =_xlfn.CONCAT(A31," Bid-Ask Adjustment") -> Bid-Ask Adjustment | C31: 0.05 | D31: $nil | E31: =IF(E11="Sale Price","$nil",-E30*$C$31) -> -43950 | F31: =IF(F11="Sale Price","$nil",-F30*$C$31) -> $nil | G31: =IF(G11="Sale Price","$nil",-G30*$C$31) -> $nil | H31: =IF(H11="Sale Price","$nil",-H30*$C$31) -> $nil | I31: =IF(I11="Sale Price","$nil",-I30*$C$31) -> $nil | J31: =IF(J11="Sale Price","$nil",-J30*$C$31) -> $nil | K31: =IF(K11="Sale Price","$nil",-K30*$C$31) -> $nil | P31: =IF(P11="Sale Price","$nil",-P30*$C$31) -> $nil
C33: Adjustment Type
B34: Adjustment Year Built | C34: Manual | D34: 0 | E34: 0 | F34: 0 | G34: 0 | H34: 0 | I34: 0 | J34: =J30*0.02 -> 17000 | K34: 0 | P34: 0
B35: Adjustment Format | C35: Manual | D35: 0 | E35: 0 | F35: 0 | G35: 0 | H35: 0 | I35: 0 | J35: 0 | K35: 0 | P35: 0
B36: Adjustment Garage | C36: Manual | D36: 0 | E36: 0 | F36: 0 | G36: 0 | H36: 0 | I36: 0 | J36: 10000 | K36: 0 | P36: 0
B37: Adjustment Bedroom | C37: Automatic | D37: 0 | E37: =($D$22-E22)*$D73 -> -2500 | F37: =($D$22-F22)*$D73 -> 0 | G37: =($D$22-G22)*$D73 -> -2500 | H37: =($D$22-H22)*$D73 -> 0 | I37: =($D$22-I22)*$D73 -> -2500 | J37: =($D$22-J22)*$D73 -> -5000 | K37: =($D$22-K22)*$D73 -> 0 | P37: =($D$22-P22)*$D73 -> -2500
B38: Adjustment Bathroom | C38: Automatic | D38: 0 | E38: =($D$23-E23)*$D$74 -> 7500 | F38: =($D$23-F23)*$D$74 -> 3750 | G38: =($D$23-G23)*$D$74 -> 0 | H38: =($D$23-H23)*$D$74 -> 7500 | I38: =($D$23-I23)*$D$74 -> 11250 | J38: =($D$23-J23)*$D$74 -> -11250 | K38: =($D$23-K23)*$D$74 -> 0 | P38: =($D$23-P23)*$D$74 -> 11250
B39: Adjustment Finishing | C39: Manual | D39: 0 | E39: 0 | F39: 0 | G39: 0 | H39: 0 | I39: 0 | J39: 0 | K39: 0 | P39: 0
B40: Adjustment Basement | C40: Manual | D40: 0 | E40: =E17*$D$77*$D$78 -> 40160 | F40: =F17*$D$77*$D$78 -> 40080 | G40: 0 | H40: =H17*$D$77*$D$78 -> 34592 | I40: =I17*$D$77*$D$78 -> 37728 | J40: 0 | K40: 0 | P40: 0
B41: Adjustment Appliances | C41: Manual | D41: 0 | E41: 0 | F41: 0 | G41: 0 | H41: 0 | I41: 10000 | J41: 0 | K41: 0 | P41: 0
B42: Adjustment Fireplace | C42: Manual | D42: 0 | E42: 0 | F42: 0 | G42: 0 | H42: 0 | I42: 0 | J42: 0 | K42: 0 | P42: 0
B43: Adjustment Neighbourhood | C43: Manual | D43: 0 | E43: 0 | F43: 0 | G43: 0 | H43: 0 | I43: 0 | J43: 0 | K43: 0 | P43: 0
B44: Adjustment backyard/deck | C44: Manual | D44: 0 | E44: 0 | F44: 0 | G44: 0 | H44: 0 | I44: 0 | J44: 0 | K44: 0 | P44: 0
B45: Adjustment Other | C45: Manual | D45: 0 | E45: 0 | F45: 0 | G45: 0 | H45: 0 | I45: 0 | J45: 0 | K45: 0 | P45: 0
B46: Total Adjustments | D46: 0 | E46: =SUM(E34:E45) -> 45160 | F46: =SUM(F34:F45) -> 43830 | G46: =SUM(G34:G45) -> -2500 | H46: =SUM(H34:H45) -> 42092 | I46: =SUM(I34:I45) -> 56478 | J46: =SUM(J34:J45) -> 10750 | K46: =SUM(K34:K45) -> 0 | P46: =SUM(P34:P45) -> 8750
B48: Adjusted Price | D48: =SUM(D30,D31,D46) -> 916000 | E48: =SUM(E30,E31,E46) -> 880210 | F48: =SUM(F30,F31,F46) -> 773830 | G48: =SUM(G30,G31,G46) -> 837500 | H48: =SUM(H30,H31,H46) -> 766992 | I48: =SUM(I30,I31,I46) -> 736378 | J48: =SUM(J30,J31,J46) -> 860750 | K48: =SUM(K30,K31,K46) -> 860000 | P48: =SUM(P30,P31,P46) -> 722940
B49: Adjusted Unit Price | D49: =IFERROR(D48/D17,"N/A") -> 391.78785 | E49: =IFERROR(E48/E17,"N/A") -> 350.68127 | F49: =IFERROR(F48/F17,"N/A") -> 308.91417 | G49: =IFERROR(G48/G17,"N/A") -> 336.07544 | H49: =IFERROR(H48/H17,"N/A") -> 354.76041 | I49: =IFERROR(I48/I17,"N/A") -> 312.28923 | J49: =IFERROR(J48/J17,"N/A") -> 356.86153 | K49: =IFERROR(K48/K17,"N/A") -> 377.68994 | P49: =IFERROR(P48/P17,"N/A") -> 355.95273
B51: Internal Valuation - Price per sq. ft.
D53: $ Per Sq. Ft. | E53: Implied Value
B54: Min | D54: =MIN($E$49:$K$49) -> 308.91417 | E54: =IFERROR(D54*$D$17,"TBD") -> 722241.33
B55: 25th Percentile | D55: =_xlfn.PERCENTILE.INC($E$49:$K$49,0.25) -> 324.18233 | E55: =IFERROR(D55*$D$17,"TBD") -> 757938.3
B56: Median | D56: =AVERAGE($E$49:$K$49) -> 342.46743 | E56: =IFERROR(D56*$D$17,"TBD") -> 800688.85
B57: Weighted Avg. Unit Price | D57: =SUM($E$48:$K$48)/SUM($E$17:$K$17) -> 341.92749 | E57: =IFERROR(D57*$D$17,"TBD") -> 799426.48
B58: 75th Percentile | D58: =_xlfn.PERCENTILE.INC($E$49:$K$49,0.75) -> 355.81097 | E58: =IFERROR(D58*$D$17,"TBD") -> 831886.04
B59: Max | D59: =MAX($E$49:$K$49) -> 377.68994 | E59: =IFERROR(D59*$D$17,"TBD") -> 883039.09
B60: SD | D60: =_xlfn.STDEV.P(E49:K49) -> 23.126369
B61: Subject Property | D61: =D49 -> 391.78785 | E61: =D48 -> 916000
B64: KV $ / sq. ft | D64: 350
B65: KV Internal Value | D65: =D64*$D$17 -> 818300
B72: Table A - Adjustment Factors
B73: Bedroom | D73: 2500
B74: Bathroom | D74: 7500
B75: Garage Parking | D75: 10000
B76: Appliances | D76: 15000
B77: Basement Adjustment ($ per Sq. Ft.) | D77: 40
B78: Basement Square Feet Estimate | D78: 0.4
B79: Basement Adjustment - Walkout | D79: 8000
B80: Games Room and Wet Bar | D80: 5000

Sheet Sheet3
B2: Civic Address | C2: Plan / Condominium Plan | D2: Block/Unit | E2: Lot | F2: Geographical Region | G2: % Complete / Cost to Complete ("%" or "Cost") | H2: Financing Category (Presold vs Speculative) | I2: Project Phase (Land, Construction, Completed) | J2: Land - Pledged LTC | K2: Const. - Pledged LTC | L2: Const. - Pledged LTV | M2: Land Cost | N2: "As Is" Value - Fully Serviced Lots - Appraised | O2: Land Value: Lesser of Cost and Appraised Value | P2: "As Complete" Appraised Value | Q2: "As Complete" Value - for LTV | R2: $Value/SQFT | S2: Lot Size (SF) | T2: Unit Size (SF AG - "as if" built) | U2: Construction Costs (Excl. Land) | V2: $Const. /SQFT | W2: Land Financing | X2: Construction Financing | Y2: Total Committed | Z2: LTV - Committed | AA2: Overall LTC - Committed | AB2: Possible Draw Amount | AC2: Initial Draw Date | AD2: Land Draw | AE2: Construction Draw | AF2: Total Amount Drawn | AG2: Net Loan Amount | AH2: Available Draw Amount | AI2: Percent Complete | AJ2: Security Value | AK2: Cost to Complete | AL2: Unfunded | AM2: Gross Amount Received | AN2: Pre-Payment Penalty | AO2: Net Paydown Amount | AP2: Payout Statement Date | AQ2: Date Funds Received | AR2: Date Discharge Sent | AS2: Notes | AT2: Price | AU2: GST | AV2: Full Price | AW2: Change Orders | AX2: Deposit | AY2: Deposit Percentage of Purchase Price | AZ2: Purchaser | BA2: Sale Price - Appraised | BB2: Sale Date | BC2: Notes
B3: 232 Aspenmere Way, Chestermere | C3: 1513280 | D3: 42 | E3: 57 | F3: Chestermere | G3: Cost | H3: Pre-Sold | I3: =IF(AI3=0,"Land",IF(AND(AI3>0,AI3<1),"Construction",IF(AI3=1,"Completed"))) -> Construction | J3: 0.55 | K3: 0.75 | L3: 0.65 | M3: 200000 | N3: 210000 | O3: =MIN(M3:N3) -> 200000 | P3: 740000 | Q3: =IF(AV3>0,MIN(P3,AV3),P3) -> 739000 | R3: =Q3/T3 -> 228.50959 | S3: 8309.7308 | T3: 3234 | U3: 426200 | V3: =U3/T3 -> 131.78726 | W3: =J3*MIN(M3:N3) -> 110000 | X3: =MAX(IF(Q3="",0,MIN(((U3+M3)*K3)-W3,(Q3*L3)-W3)),0) -> 359650 | Y3: =W3+X3 -> 469650 | Z3: =IF(Q3>0,Y3/Q3,Y3/N3) -> 0.63552097 | AA3: =IF(Q3>0,Y3/(M3+U3),Y3/M3) -> 0.75 | AB3: =ROUND(IF(Q3>0,IF(G3="%",W3+X3*AI3,W3+MAX((O3+(U3*AI3))-(O3+U3-X3),0)),W3),2) -> 459847.4 | AC3: 44008 | AD3: 110000 | AE3: =243297.4+32817.4+53275 -> 329389.8 | AF3: =SUM(AD3:AE3) -> 439389.8 | AG3: =AF3-AO3 -> 0 | AH3: =AB3-AF3 -> 20457.6 | AI3: 0.977 | AJ3: =IF(AM3>0,0,N3+(Q3-N3)*AI3) -> 0 | AK3: =(1-AI3)*U3 -> 9802.6 | AL3: =Y3-AF3 -> 30260.2 | AM3: 439389.8 | AO3: =AM3-AN3 -> 439389.8 | AP3: 44069 | AQ3: 44074 | AR3: 44097 | AT3: =AV3/1.05 -> 703809.52 | AU3: =AT3*0.05 -> 35190.476 | AV3: 739000 | AX3: 70000 | AY3: =AX3/AV3 -> 0.094722598 | AZ3: Louis M Yhap & Bibi S Yhap | BA3: =IFERROR(AV3/Q3,0) -> 1 | BB3: 43800
B4: 728 Marina Drive, Chestermere | C4: 1910205 | D4: 1 | E4: 2 | F4: Chestermere | G4: Cost | H4: Pre-Sold | I4: =IF(AI4=0,"Land",IF(AND(AI4>0,AI4<1),"Construction",IF(AI4=1,"Completed"))) -> Construction | J4: 0.55 | K4: 0.75 | L4: 0.65 | M4: 204389 | N4: 180000 | O4: =MIN(M4:N4) -> 180000 | P4: 705000 | Q4: =IF(AV4>0,MIN(P4,AV4),P4) -> 698500 | R4: =Q4/T4 -> 230.83278 | S4: =489*10.7639 -> 5263.5471 | T4: 3026 | U4: 400200 | V4: =U4/T4 -> 132.2538 | W4: =J4*MIN(M4:N4) -> 99000 | X4: =MAX(IF(Q4="",0,MIN(((U4+M4)*K4)-W4,(Q4*L4)-W4)),0) -> 354441.75 | Y4: =W4+X4 -> 453441.75 | Z4: =IF(Q4>0,Y4/Q4,Y4/N4) -> 0.649165 | AA4: =IF(Q4>0,Y4/(M4+U4),Y4/M4) -> 0.75 | AB4: =ROUND(IF(Q4>0,IF(G4="%",W4+X4*AI4,W4+MAX((O4+U4*AI4)-(O4+U4-X4),0)),W4),2) -> 346988.55 | AC4: 44008 | AD4: 99000 | AE4: =155142.15+17608.8+54827.4+9604.8+10805.4 -> 247988.55 | AF4: =SUM(AD4:AE4) -> 346988.55 | AG4: =AF4-AO4 -> 0 | AH4: =AB4-AF4 -> 0 | AI4: 0.734 | AJ4: =IF(AM4>0,0,O4+(Q4-O4)*AI4) -> 0 | AK4: =(1-AI4)*U4 -> 106453.2 | AL4: =Y4-AF4 -> 106453.2 | AM4: 346988.55 | AO4: =AM4-AN4 -> 346988.55 | AP4: 44102 | AQ4: 44109 | AR4: 44134 | AT4: =AV4/1.05 -> 665238.1 | AU4: =AT4*0.05 -> 33261.905 | AV4: 698500 | AX4: 70000 | AY4: =AX4/AV4 -> 0.10021475 | AZ4: Sukhjeet Singh & Rajandeep Kaur Sandhu | BA4: =IFERROR(AV4/Q4,0) -> 1 | BB4: 43807
B5: 732 Marina Drive | C5: 1910205 | D5: 1 | E5: 3 | F5: Chestermere | G5: Cost | H5: Pre-Sold | I5: =IF(AI5=0,"Land",IF(AND(AI5>0,AI5<1),"Construction",IF(AI5=1,"Completed"))) -> Construction | J5: 0.55 | K5: 0.75 | L5: 0.65 | M5: 204389 | N5: 175000 | O5: =MIN(M5:N5) -> 175000 | P5: 655000 | Q5: =IF(AV5>0,MIN(P5,AV5),P5) -> 648375 | R5: =Q5/T5 -> 251.99184 | S5: 5285 | T5: 2573 | U5: 331300 | V5: =U5/T5 -> 128.7602 | W5: =J5*MIN(M5:N5) -> 96250 | X5: =MAX(IF(Q5="",0,MIN(((U5+M5)*K5)-W5,(Q5*L5)-W5)),0) -> 305516.75 | Y5: =W5+X5 -> 401766.75 | Z5: =IF(Q5>0,Y5/Q5,Y5/N5) -> 0.61965182 | AA5: =IF(Q5>0,Y5/(M5+U5),Y5/M5) -> 0.75 | AB5: =ROUND(IF(Q5>0,IF(G5="%",W5+X5*AI5,W5+MAX((O5+U5*AI5)-(O5+U5-X5),0)),W5),2) -> 315297.45 | AC5: 44068 | AD5: 96250 | AE5: =130921.65+41412.5+46713.3 -> 219047.45 | AF5: =SUM(AD5:AE5) -> 315297.45 | AG5: =AF5-AO5 -> 0 | AH5: =AB5-AF5 -> 0 | AI5: 0.739 | AJ5: =IF(AM5>0,0,O5+(Q5-O5)*AI5) -> 0 | AK5: =(1-AI5)*U5 -> 86469.3 | AL5: =Y5-AF5 -> 86469.3 | AM5: =315294.45+3 -> 315297.45 | AO5: =AM5-AN5 -> 315297.45 | AP5: 44111 | AQ5: 44123 | AR5: 44151 | AT5: =AV5/1.05 -> 617500 | AU5: =AV5-AT5 -> 30875 | AV5: 648375 | AX5: 65000 | AY5: =AX5/AV5 -> 0.10025063 | AZ5: Dalwinder Bassi and Baljiit Bassi | BA5: =AV5/P5 -> 0.9898855 | BB5: 43845
B6: 296 Aspenmere Way, Chestermere | C6: 1513280 | D6: 42 | E6: 73 | F6: Chestermere | G6: Cost | H6: Pre-Sold | I6: =IF(AI6=0,"Land",IF(AND(AI6>0,AI6<1),"Construction",IF(AI6=1,"Completed"))) -> Construction | J6: 0.55 | K6: 0.75 | L6: 0.65 | M6: 205000 | N6: 190000 | O6: =MIN(M6:N6) -> 190000 | P6: 730000 | Q6: =IF(AV6>0,MIN(P6,AV6),P6) -> 730000 | R6: =Q6/T6 -> 226.91949 | S6: 5812.506 | T6: 3217 | U6: 395600 | V6: =U6/T6 -> 122.97171 | W6: =J6*MIN(M6:N6) -> 104500 | X6: =MAX(IF(Q6="",0,MIN(((U6+M6)*K6)-W6,(Q6*L6)-W6)),0) -> 345950 | Y6: =W6+X6 -> 450450 | Z6: =IF(Q6>0,Y6/Q6,Y6/N6) -> 0.61705479 | AA6: =IF(Q6>0,Y6/(M6+U6),Y6/M6) -> 0.75 | AB6: =ROUND(IF(Q6>0,IF(G6="%",W6+X6*AI6,W6+MAX((O6+U6*AI6)-(O6+U6-X6),0)),W6),2) -> 362626.8 | AC6: 44008 | AD6: 104500 | AE6: =22349.2+54197.2+49845.6+46285.2+53801.6+31648 -> 258126.8 | AF6: =SUM(AD6:AE6) -> 362626.8 | AG6: =AF6-AO6 -> 0 | AH6: =AB6-AF6 -> 0 | AI6: 0.778 | AJ6: =IF(AM6>0,0,O6+(Q6-O6)*AI6) -> 0 | AK6: =(1-AI6)*U6 -> 87823.2 | AL6: =Y6-AF6 -> 87823.2 | AM6: 362626.8 | AN6: 0 | AO6: =AM6-AN6 -> 362626.8 | AQ6: 44130 | AR6: 44162 | AT6: =AV6/1.05 -> 695238.1 | AU6: =AT6*0.05 -> 34761.905 | AV6: 730000 | AX6: 50000 | AY6: =AX6/AV6 -> 0.068493151 | AZ6: Arshdeep Singh Badesha & Navkiran Kaur Badesha | BA6: =IFERROR(AV6/Q6,0) -> 1 | BB6: 43797
B7: 736 Marina Drive | C7: 1910205 | D7: 1 | E7: 4 | F7: Chestermere | G7: Cost | H7: Pre-Sold | I7: =IF(AI7=0,"Land",IF(AND(AI7>0,AI7<1),"Construction",IF(AI7=1,"Completed"))) -> Construction | J7: 0.55 | K7: 0.75 | L7: 0.65 | M7: 204389 | N7: 180000 | O7: =MIN(M7:N7) -> 180000 | P7: 625000 | Q7: =IF(AV68>0,MIN(P7,AV68),P7) -> 625000 | R7: =Q7/T7 -> 255.41479 | S7: 5264 | T7: 2447 | U7: 304700 | V7: =U7/T7 -> 124.51982 | W7: =J7*MIN(M7:N7) -> 99000 | X7: =MAX(IF(Q7="",0,MIN(((U7+M7)*K7)-W7,(Q7*L7)-W7)),0) -> 282816.75 | Y7: =W7+X7 -> 381816.75 | Z7: =IF(Q7>0,Y7/Q7,Y7/N7) -> 0.6109068 | AA7: =IF(Q7>0,Y7/(M7+U7),Y7/M7) -> 0.75 | AB7: =ROUND(IF(Q7>0,IF(G7="%",W7+X7*AI7,W7+MAX((O7+U7*AI7)-(O7+U7-X7),0)),W7),2) -> 283703.35 | AC7: 44068 | AD7: 99000 | AE7: =100910.85+29555.9+54236.6 -> 184703.35 | AF7: =SUM(AD7:AE7) -> 283703.35 | AG7: =AF7-AO7 -> 0 | AH7: =AB7-AF7 -> 0 | AI7: 0.678 | AJ7: =IF(AM7>0,0,O7+(Q7-O7)*AI7) -> 0 | AK7: =(1-AI7)*U7 -> 98113.4 | AL7: =Y7-AF7 -> 98113.4 | AM7: 283703.35 | AO7: =AM7-AN7 -> 283703.35 | AP7: 44111 | AQ7: 44137 | AR7: 44162 | AT7: =AV7/1.05 -> 595238.1 | AU7: =AV7-AT7 -> 29761.905 | AV7: 625000 | AX7: =25000+31250+100000 -> 156250 | AY7: =AX7/AV7 -> 0.25 | AZ7: Jobandeep Singh Gill & Amandeep Kaur Gill | BA7: =IFERROR(AV7/P7,0) -> 1 | BB7: 43801
B8: 741 Marina Drive, Chestermere | C8: 1910205 | D8: 2 | E8: 5 | F8: Chestermere | G8: Cost | H8: Pre-sold | I8: =IF(AI8=0,"Land",IF(AND(AI8>0,AI8<1),"Construction",IF(AI8=1,"Completed"))) -> Completed | J8: 0.55 | K8: 0.75 | L8: 0.65 | M8: 214757 | N8: 175000 | O8: =MIN(M8:N8) -> 175000 | P8: 622000 | Q8: =IF(AV8>0,MIN(P8,AV8),P8) -> 622000 | R8: =Q8/T8 -> 256.60066 | S8: =464*10.7639 -> 4994.4496 | T8: 2424 | U8: 373978.81 | V8: =U8/T8 -> 154.28169 | W8: =J8*MIN(M8:N8) -> 96250 | X8: =MAX(IF(Q8="",0,MIN(((U8+M8)*K8)-W8,(Q8*L8)-W8)),0) -> 308050 | Y8: =W8+X8 -> 404300 | Z8: =IF(Q8>0,Y8/Q8,Y8/N8) -> 0.65 | AA8: =IF(Q8>0,Y8/(M8+U8),Y8/M8) -> 0.68672568 | AB8: =ROUND(IF(Q8>0,IF(G8="%",W8+X8*AI8,W8+MAX((O8+U8*AI8)-(O8+U8-X8),0)),W8),2) -> 404300 | AC8: 44008 | AD8: 87500 | AE8: =285700+23532.5+23117.5 -> 332350 | AF8: =SUM(AD8:AE8) -> 419850 | AG8: =AF8-AO8 -> 0 | AH8: =AB8-AF8 -> -15550 | AI8: 1 | AJ8: =IF(AM8>0,0,O8+(Q8-O8)*AI8) -> 0 | AK8: =(1-AI8)*U8 -> 0 | AL8: =Y8-AF8 -> -15550 | AM8: 419850 | AO8: =AM8-AN8 -> 419850 | AP8: 44174 | AQ8: 44180 | AR8: 44211 | AT8: =AV8/1.05 -> 600000 | AU8: =AT8*0.05 -> 30000 | AV8: 630000 | AX8: 63000 | AY8: =AX8/AV8 -> 0.1 | AZ8: Avtar Sidhu & Jasvir Sidhu | BA8: =IFERROR(AV8/P8,0) -> 1.0128617 | BB8: 44077
B9: 729 Marina Drive | C9: 1910205 | D9: 2 | E9: 2 | F9: Chestermere | G9: Cost | H9: Pre-Sold | I9: =IF(AI9=0,"Land",IF(AND(AI9>0,AI9<1),"Construction",IF(AI9=1,"Completed"))) -> Construction | J9: 0.6 | K9: 0.775 | L9: 0.675 | M9: 205234 | N9: 180000 | O9: =MIN(M9:N9) -> 180000 | P9: 668000 | Q9: =IF(AV9>0,MIN(P9,AV9),P9) -> 665000 | R9: =Q9/T9 -> 221.44522 | S9: 4897 | T9: 3003 | U9: 375400 | V9: =U9/T9 -> 125.00833 | W9: =J9*MIN(M9:N9) -> 108000 | X9: =MAX(IF(Q9="",0,MIN(((U9+M9)*K9)-W9,(Q9*L9)-W9)),0) -> 340875 | Y9: =W9+X9 -> 448875 | Z9: =IF(Q9>0,Y9/Q9,Y9/N9) -> 0.675 | AA9: =IF(Q9>0,Y9/(M9+U9),Y9/M9) -> 0.77307736 | AB9: =ROUND(IF(Q9>0,IF(G9="%",W9+X9*AI9,W9+MAX((O9+U9*AI9)-(O9+U9-X9),0)),W9),2) -> 416590.6 | AC9: 44154 | AD9: 108000 | AE9: =143039.2+70199.8+95351.6 -> 308590.6 | AF9: =SUM(AD9:AE9) -> 416590.6 | AG9: =AF9-AO9 -> 0 | AH9: =AB9-AF9 -> 0 | AI9: 0.914 | AJ9: =IF(AM9>0,0,O9+(Q9-O9)*AI9) -> 0 | AK9: =(1-AI9)*U9 -> 32284.4 | AL9: =Y9-AF9 -> 32284.4 | AM9: 416590.6 | AO9: =AM9-AN9 -> 416590.6 | AP9: 44223 | AQ9: 44228 | AT9: =AV9/1.05 -> 633333.33 | AU9: =AT9*0.05 -> 31666.667 | AV9: 665000 | AX9: =5000+94750 -> 99750 | AY9: =AX9/AV9 -> 0.15 | AZ9: Gurvir Sidhu | BA9: =IFERROR(AV9/P9,0) -> 0.99550898 | BB9: 44037
B10: 744 Marina Drive | C10: 1910205 | D10: 1 | E10: 6 | F10: Chestermere | G10: Cost | H10: Speculative | I10: =IF(AI10=0,"Land",IF(AND(AI10>0,AI10<1),"Construction",IF(AI10=1,"Completed"))) -> Construction | J10: 0.5 | K10: 0.725 | L10: 0.625 | M10: 211331 | N10: 200000 | O10: =MIN(M10:N10) -> 200000 | P10: 585000 | Q10: =IF(AV10>0,MIN(P10,AV10),P10) -> 585000 | R10: =Q10/T10 -> 253.68604 | S10: 5242 | T10: 2306 | U10: 318700 | V10: =U10/T10 -> 138.20468 | W10: =J10*MIN(M10:N10) -> 100000 | X10: =MAX(IF(Q10="",0,MIN(((U10+M10)*K10)-W10,(Q10*L10)-W10)),0) -> 265625 | Y10: =W10+X10 -> 365625 | Z10: =IF(Q10>0,Y10/Q10,Y10/N10) -> 0.625 | AA10: =IF(Q10>0,Y10/(M10+U10),Y10/M10) -> 0.68981814 | AB10: =ROUND(IF(Q10>0,IF(G10="%",W10+X10*AI10,W10+MAX((O10+U10*AI10)-(O10+U10-X10),0)),W10),2) -> 361800.6 | AC10: 44154 | AD10: 100000 | AE10: =180850.8+84774.2 -> 265625 | AF10: =SUM(AD10:AE10) -> 365625 | AG10: =AF10-AO10 -> 0 | AH10: =AB10-AF10 -> -3824.4 | AI10: 0.988 | AJ10: =IF(AM10>0,0,O10+(Q10-O10)*AI10) -> 0 | AK10: =(1-AI10)*U10 -> 3824.4 | AL10: =Y10-AF10 -> 0 | AM10: 365625 | AO10: =AM10-AN10 -> 365625 | AP10: 44236 | AQ10: 44244 | AR10: 44274 | AT10: =AV10/1.05 -> 588571.43 | AU10: =AV10-AT10 -> 29428.571 | AV10: 618000 | AX10: 30000 | AY10: =AX10/AV10 -> 0.048543689 | AZ10: Bhawanjot & Sharandeep Grewal | BA10: =IFERROR(AV10/P10,0) -> 1.0564103 | BB10: 44208
B11: 317 Aspenmere Way, Chestermere | C11: 1513280 | D11: 44 | E11: 20 | F11: Chestermere | G11: Cost | H11: Pre-Sold | I11: Construction | J11: 0.55 | K11: 0.75 | L11: 0.65 | M11: 205000 | N11: 200000 | O11: 200000 | P11: 780000 | Q11: 780000 | R11: 237.37066 | S11: 5511.1168 | T11: 3286 | U11: 407500 | V11: 124.01096 | W11: 110000 | X11: 349375 | Y11: 459375 | Z11: 0.58894231 | AA11: 0.75 | AB11: 434925 | AC11: 44008 | AD11: 110000 | AE11: 290695 | AF11: 400695 | AG11: 0 | AH11: 34230 | AI11: 0.94 | AJ11: 0 | AK11: 24450 | AL11: 58680 | AM11: 400695 | AO11: 400695 | AP11: 44067 | AQ11: 44068 | AT11: 743333.33 | AU11: 37166.667 | AV11: 780500 | AX11: 55000 | AY11: 0.070467649 | AZ11: Jasprett Singh Sandhu & Rajwinder Kaur Sandhu | BA11: 1.000641 | BB11: 43791
B12: 488 Muirfield Crescent, Lyalta | C12: 0811158 | D12: 4 | E12: N/A | F12: Rural Alberta | G12: Cost | H12: Speculative | I12: Completed | J12: 0.5 | K12: 0.675 | L12: 0.575 | M12: 134400 | N12: 70000 | O12: 70000 | P12: 463000 | Q12: 463000 | R12: 314.11126 | S12: 7803.8275 | T12: 1474 | U12: 271200 | V12: 183.98915 | W12: 35000 | X12: 231225 | Y12: 266225 | Z12: 0.575 | AA12: 0.65637327 | AB12: 266225 | AC12: 44008 | AD12: 35000 | AE12: 230851.25 | AF12: 265851.25 | AG12: 0 | AH12: 373.75 | AI12: 1 | AJ12: 0 | AK12: 0 | AL12: 373.75 | AM12: 265851.25 | AO12: 265851.25 | AP12: 44236 | AQ12: 44257 | AR12: 44295 | AT12: 449523.81 | AU12: 22476.19 | AV12: 472000 | AX12: 15000 | AY12: 0.031779661 | AZ12: Sean Hynes and Joanne Byrne | BA12: 1.0194384 | BB12: 44147
B13: 725 Marina Drive | C13: 1910205 | D13: 2 | E13: 1 | F13: Chestermere | G13: Cost | H13: Pre-Sold | I13: Construction | J13: 0.6 | K13: 0.775 | L13: 0.675 | M13: 205234 | N13: 180000 | O13: 180000 | P13: 684000 | Q13: 683500 | R13: 223.5121 | S13: 4898 | T13: 3058 | U13: 383900 | V13: 125.53957 | W13: 108000 | X13: 348578.85 | Y13: 456578.85 | Z13: 0.66800124 | AA13: 0.775 | AB13: 412430.35 | AC13: 44154 | AD13: 108000 | AE13: 304430.35 | AF13: 412430.35 | AG13: 0 | AH13: 0 | AI13: 0.885 | AJ13: 0 | AK13: 44148.5 | AL13: 44148.5 | AM13: 412430.35 | AO13: 412430.35 | AP13: 44300 | AQ13: 44305 | AR13: 44335 | AT13: 650952.38 | AU13: 32547.619 | AV13: 683500 | AX13: 34175 | AY13: 0.05 | AZ13: Kulbir Singh, Pawanpreet Singh & Bhanwarpreet Singh | BA13: 0.99926901 | BB13: 43990
B14: 1512 25 Avenue SW, Calgary | C14: 2011851 | D14: 3 | E14: N/A | F14: Calgary | G14: Cost | H14: Speculative | I14: Construction | J14: 0.5 | K14: 0.725 | L14: 0.625 | M14: 153750 | N14: 160000 | O14: 153750 | P14: 539900 | Q14: 538000 | R14: 381.83109 | S14: 1400 | T14: 1409 | U14: 280901.07 | V14: 199.36201 | W14: 76875 | X14: 238247.03 | Y14: 315122.03 | Z14: 0.58572867 | AA14: 0.725 | AB14: 285908.32 | AC14: 44008 | AD14: 76875 | AE14: 209033.32 | AF14: 285908.32 | AG14: 0 | AH14: 0 | AI14: 0.896 | AJ14: 0 | AK14: 29213.711 | AL14: 29213.707 | AM14: 285908.32 | AO14: 285908.32 | AP14: 44305 | AQ14: 44306 | AR14: 44335 | AT14: 512380.95 | AU14: 25619.048 | AV14: 538000 | AX14: 10000 | AY14: 0.018587361 | AZ14: Tanya Morahan | BA14: 0.99648083 | BB14: 44257
B15: 130 Kinniburgh Crescent | C15: 1812008 | D15: 11 | E15: 42 | F15: Chestermere | G15: Cost | H15: Pre-Sold | I15: Construction | J15: 0.6 | K15: 0.775 | L15: 0.675 | M15: 187000 | N15: 215000 | O15: 187000 | P15: 685000 | Q15: 685000 | R15: 230.71741 | S15: 5748 | T15: 2969 | U15: 388300 | V15: 130.78478 | W15: 112200 | X15: 333657.5 | Y15: 445857.5 | Z15: 0.65088686 | AA15: 0.775 | AB15: 427995.7 | AC15: 44154 | AD15: 93500 | AE15: 334495.7 | AF15: 427995.7 | AG15: 0 | AH15: 0 | AI15: 0.954 | AJ15: 0 | AK15: 17861.8 | AL15: 17861.8 | AM15: 427995.7 | AO15: 427995.7 | AP15: 44330 | AQ15: 44341 | AR15: 44375 | AT15: 669828.57 | AU15: 33491.429 | AV15: 703320 | AX15: 10000 | AY15: 0.014218279 | AZ15: Rajwinder Bajwa & Rajkamal Bajwa | BA15: 1.0267445 | BB15: 44195
B16: 1510 25 Avenue SW, Calgary | C16: 2011851 | D16: 4 | E16: N/A | F16: Calgary | G16: Cost | H16: Speculative | I16: Completed | J16: 0.5 | K16: 0.725 | L16: 0.625 | M16: 153750 | N16: 160000 | O16: 153750 | P16: 539900 | Q16: 537000 | R16: 381.12136 | S16: 1400 | T16: 1409 | U16: 280901.07 | V16: 199.36201 | W16: 76875 | X16: 238247.03 | Y16: 315122.03 | Z16: 0.58681942 | AA16: 0.725 | AB16: 309223.1 | AC16: 44008 | AD16: 76875 | AE16: 238247.03 | AF16: 315122.03 | AG16: 0 | AH16: -5898.93 | AI16: 0.979 | AJ16: 0 | AK16: 5898.9225 | AL16: -0.0032687991 | AM16: 315122.03 | AO16: 315122.03 | AP16: 44390 | AQ16: 44398 | AR16: 44420 | AT16: 511428.57 | AU16: 25571.429 | AV16: 537000 | AX16: 10000 | AY16: 0.018621974 | AZ16: Rejish Thomas & Ratika Srivastava | BA16: 0.99462863 | BB16: 44278
B17: 1514 25 Avenue SW, Calgary | C17: 2011851 | D17: 2 | E17: N/A | F17: Calgary | G17: Cost | H17: Speculative | I17: Completed | J17: 0.5 | K17: 0.725 | L17: 0.625 | M17: 153750 | N17: 160000 | O17: 153750 | P17: 539900 | Q17: 532000 | R17: 377.57275 | S17: 1400 | T17: 1409 | U17: 280901.07 | V17: 199.36201 | W17: 76875 | X17: 238247.03 | Y17: 315122.03 | Z17: 0.59233464 | AA17: 0.725 | AB17: 309223.1 | AC17: 44008 | AD17: 76875 | AE17: 238247.03 | AF17: 315122.03 | AG17: 0 | AH17: -5898.93 | AI17: 0.979 | AJ17: 0 | AK17: 5898.9225 | AL17: -0.0032687991 | AM17: 315122.03 | AO17: 315122.03 | AQ17: 44393 | AR17: 44420 | AT17: 506666.67 | AU17: 25333.333 | AV17: 532000 | AX17: 10000 | AY17: 0.018796992 | AZ17: Carson Kotnyek | BA17: 0.98536766 | BB17: 44344
B18: 1516 25 Avenue SW, Calgary | C18: 2011851 | D18: 1 | E18: N/A | F18: Calgary | G18: Cost | H18: Speculative | I18: Completed | J18: 0.5 | K18: 0.725 | L18: 0.625 | M18: 153750 | N18: 160000 | O18: 153750 | P18: 539900 | Q18: 539900 | R18: 383.17956 | S18: 1400 | T18: 1409 | U18: 280901.07 | V18: 199.36201 | W18: 76875 | X18: 238247.03 | Y18: 315122.03 | Z18: 0.5836674 | AA18: 0.725 | AB18: 309223.1 | AC18: 44008 | AD18: 76875 | AE18: 238247.03 | AF18: 315122.03 | AG18: 0 | AH18: -5898.93 | AI18: 0.979 | AJ18: 0 | AK18: 5898.9225 | AL18: -0.0032687988 | AM18: 315122.03 | AO18: 315122.03 | AP18: 44392 | AQ18: 44398 | AR18: 44420 | AT18: 519047.62 | AU18: 25952.381 | AV18: 545000 | AX18: 50000 | AY18: 0.091743119 | AZ18: Rajiv Srivastava | BA18: 1.0094462 | BB18: 44305
B19: 40 Waterford Heights | C19: 2110528 | D19: 2 | E19: 5 | F19: Chestermere | G19: Cost | H19: Speculative | I19: Completed | J19: 0.5 | K19: 0.725 | L19: 0.625 | M19: 232800 | N19: 240000 | O19: 232800 | P19: 705000 | Q19: 705000 | R19: 306.25543 | S19: 4984 | T19: 2302 | U19: 366900 | V19: 159.38315 | W19: 116400 | X19: 318382.5 | Y19: 434782.5 | Z19: 0.61671277 | AA19: 0.725 | AB19: 428545.2 | AC19: 44314 | AD19: 116400 | AE19: 318382.5 | AF19: 434782.5 | AG19: 0 | AH19: -6237.3 | AI19: 0.983 | AJ19: 0 | AK19: 6237.3 | AL19: 0 | AM19: 434782.5 | AO19: 434782.5 | AP19: 44418 | AQ19: 44424 | AR19: 44456 | AT19: 723809.52 | AU19: 36190.476 | AV19: 760000 | AZ19: Patrick Hanly & Aliya Hanly | BA19: 1.0780142 | BB19: 44293
B20: 225 Marina Key | C20: 1910205 | D20: 2 | E20: 24 | F20: Chestermere | G20: Cost | H20: Pre-Sold | I20: Construction | J20: 0.6 | K20: 0.775 | L20: 0.675 | M20: 190000 | N20: 135000 | O20: 135000 | P20: 465000 | Q20: 465000 | R20: 226.05737 | S20: 4542.3658 | T20: 2057 | U20: 236200 | V20: 114.82742 | W20: 81000 | X20: 232875 | Y20: 313875 | Z20: 0.675 | AA20: 0.73645002 | AB20: 311985.4 | AC20: 44281 | AD20: 67500 | AE20: 246375 | AF20: 313875 | AG20: 0 | AH20: -1889.6 | AI20: 0.992 | AJ20: 0 | AK20: 1889.6 | AL20: 0 | AM20: 313875 | AO20: 313875 | AP20: 44431 | AQ20: 44438 | AR20: 44462 | AT20: 466666.67 | AU20: 23333.333 | AV20: 490000 | AX20: 10000 | AY20: 0.020408163 | AZ20: Patrick McGrath | BA20: 1.0537634 | BB20: 44285 | BC20: Pre-sale purchaser mortgage financing approval letter from TD has been obtained
B21: 229 Marina Key | C21: 1910205 | D21: 2 | E21: 25 | F21: Chestermere | G21: Cost | H21: Pre-Sold | I21: Construction | J21: 0.6 | K21: 0.775 | L21: 0.675 | M21: 190000 | N21: 140000 | O21: 140000 | P21: 485000 | Q21: 479900.4 | R21: 221.56066 | S21: 6286.1176 | T21: 2166 | U21: 242500 | V21: 111.95753 | W21: 84000 | X21: 239932.77 | Y21: 323932.77 | Z21: 0.675 | AA21: 0.7489775 | AB21: 321750.27 | AC21: 44281 | AD21: 84000 | AE21: 239932.77 | AF21: 323932.77 | AG21: 0 | AH21: -2182.5 | AI21: 0.991 | AJ21: 0 | AK21: 2182.5 | AL21: 0 | AM21: 323932.77 | AO21: 323932.77 | AP21: 44431 | AQ21: 44435 | AR21: 44462 | AT21: 457048 | AU21: 22852.4 | AV21: 479900.4 | AX21: 25750 | AY21: 0.053656967 | AZ21: Steven Anthony Douglas | BA21: 0.98948536 | BB21: 44048
B22: 733 Marina Drive | C22: 1910205 | D22: 2 | E22: 3 | F22: Chestermere | G22: Cost | H22: Pre-Sold | I22: Construction | J22: 0.6 | K22: 0.775 | L22: 0.675 | M22: 205234 | N22: 192000 | O22: 192000 | P22: 577000 | Q22: 577000 | R22: 288.9334 | S22: 4898 | T22: 1997 | U22: 282100 | V22: 141.26189 | W22: 115200 | X22: 262483.85 | Y22: 377683.85 | Z22: 0.65456473 | AA22: 0.775 | AB22: 376273.35 | AC22: 44281 | AD22: 115200 | AE22: 262483.85 | AF22: 377683.85 | AG22: 0 | AH22: -1410.5 | AI22: 0.995 | AJ22: 0 | AK22: 1410.5 | AL22: 0 | AM22: 377683.85 | AO22: 377683.85 | AP22: 44447 | AQ22: 44452 | AR22: 44477 | AT22: 549523.8 | AU22: 27476.2 | AV22: 577000 | AX22: 40000 | AY22: 0.06932409 | AZ22: Alexandra Gingras & Brad Kraus | BA22: 1 | BB22: 44164
B23: 44 Waterford Heights | C23: 2110528 | D23: 2 | E23: 4 | F23: Chestermere | G23: Cost | H23: Pre-Sold | I23: Construction | J23: 0.6 | K23: 0.775 | L23: 0.675 | M23: 232800 | N23: 240000 | O23: 232800 | P23: 890000 | Q23: 890000 | R23: 286.35779 | S23: 5414 | T23: 3108 | U23: 521400 | V23: 167.76062 | W23: 139680 | X23: 400320 | Y23: 540000 | Z23: 0.60674157 | AA23: 0.71599045 | AB23: 515494.2 | AC23: 44314 | AD23: 139680 | AE23: 375814.2 | AF23: 515494.2 | AG23: 0 | AH23: 0 | AI23: 0.953 | AJ23: 0 | AK23: 24505.8 | AL23: 24505.8 | AM23: 515494.2 | AO23: 515494.2 | AP23: 44469 | AQ23: 44473 | AR23: 44491 | AT23: 850476.19 | AU23: 42523.81 | AV23: 893000 | AX23: 177000 | AY23: 0.19820829 | AZ23: Gulvinder Singh Khosa | BA23: 1.0033708 | BB23: 44063
B24: 74 Waterford Road | C24: 2110528 | D24: 6 | E24: 19 | F24: Chestermere | G24: Cost | H24: Pre-Sold | I24: Construction | J24: 0.6 | K24: 0.775 | L24: 0.675 | M24: 191250 | N24: 185000 | O24: 185000 | P24: 550000 | Q24: 550000 | R24: 258.70179 | S24: 5185 | T24: 2126 | U24: 355400 | V24: 167.16839 | W24: 111000 | X24: 260250 | Y24: 371250 | Z24: 0.675 | AA24: 0.67913656 | AB24: 329668.2 | AC24: 44314 | AD24: 111000 | AE24: 218668.2 | AF24: 329668.2 | AG24: 0 | AH24: 0 | AI24: 0.883 | AJ24: 0 | AK24: 41581.8 | AL24: 41581.8 | AM24: 329668.2 | AO24: 329668.2 | AP24: 44477 | AQ24: 44484 | AR24: 44519 | AT24: 571955.44 | AU24: 28597.772 | AV24: 600553.21 | AX24: 33500 | AY24: 0.055781901 | AZ24: Deepak Lodhia & Chandni Nitin Rama | BA24: 1.0919149 | BB24: 44023 | BC24: Pre-sale purchaser mortgage financing approval letter has been obtained
B25: 61 Waterford Road | C25: 2110528 | D25: 2 | E25: 18 | F25: Chestermere | G25: Cost | H25: Pre-Sold | I25: Construction | J25: 0.6 | K25: 0.775 | L25: 0.675 | M25: 218250 | N25: 200000 | O25: 200000 | P25: 820000 | Q25: 820000 | R25: 304.49313 | S25: 4886.8106 | T25: 2693 | U25: 467400 | V25: 173.56108 | W25: 120000 | X25: 411378.75 | Y25: 531378.75 | Z25: 0.64802287 | AA25: 0.775 | AB25: 489312.75 | AC25: 44421 | AD25: 120000 | AE25: 369312.75 | AF25: 489312.75 | AG25: 0 | AH25: 0 | AI25: 0.91 | AJ25: 0 | AK25: 42066 | AL25: 42066 | AM25: 489312.75 | AO25: 489312.75 | AP25: 44511 | AQ25: 44523 | AR25: 44553 | AT25: 780952.38 | AU25: 39047.619 | AV25: 820000 | AX25: 82000 | AY25: 0.1 | AZ25: Mavindeep Gill & Sandeep Gill | BA25: 1 | BB25: 44209
B26: 724 Marina Drive | C26: 1910205 | D26: 1 | E26: 1 | F26: Chestermere | G26: Cost | H26: Pre-Sold | I26: Construction | J26: 0.6 | K26: 0.775 | L26: 0.675 | M26: 204077 | N26: 200000 | O26: 200000 | P26: 715000 | Q26: 713102.25 | R26: 271.658 | S26: 5259 | T26: 2625 | U26: 380400 | V26: 144.91429 | W26: 120000 | X26: 332969.67 | Y26: 452969.67 | Z26: 0.63520999 | AA26: 0.775 | AB26: 389062.48 | AC26: 44314 | AD26: 120000 | AE26: 269062.48 | AF26: 389062.48 | AG26: 0 | AH26: 0 | AI26: 0.832 | AJ26: 0 | AK26: 63907.2 | AL26: 63907.195 | AM26: 389062.48 | AO26: 389062.48 | AP26: 44529 | AQ26: 44547 | AR26: 44210 | AT26: 679145 | AU26: 33957.25 | AV26: 713102.25 | AX26: 67000 | AY26: 0.09395567 | AZ26: Sylvester Francis & Manveen Reen | BA26: 0.9973458 | BB26: 44140
B27: 7 North Bridges Road, Langdon | C27: 2011558 | D27: 2 | E27: 2 | F27: Langdon | G27: Cost | H27: Speculative | I27: Completed | J27: 0.5 | K27: 0.7 | L27: 0.6 | M27: 170000 | N27: 165000 | O27: 165000 | P27: 675000 | Q27: 675000 | R27: 373.13433 | S27: 8385 | T27: 1809 | U27: 433100 | V27: 239.41404 | W27: 82500 | X27: 277500 | Y27: 360000 | Z27: 0.53333333 | AA27: 0.59691593 | AB27: 337045.7 | AC27: 44154 | AD27: 82500 | AE27: 239545.7 | AF27: 322045.7 | AG27: 0 | AH27: 15000 | AI27: 0.947 | AJ27: 0 | AK27: 22954.3 | AL27: 37954.3 | AM27: 322045.7 | AO27: 0 | AP27: 44545 | AQ27: 44550 | AR27: 44210 | AT27: 785677.38 | AU27: 39283.869 | AV27: 824961.25 | AX27: 82496.25 | AY27: 0.10000015 | AZ27: Kathy & John Klassen | BA27: 1.2221648 | BB27: 44524
B28: 77 Waterford Road | C28: 2110528 | D28: 2 | E28: 22 | F28: Chestermere | G28: Cost | H28: Pre-Sold | I28: Construction | J28: 0.6 | K28: 0.775 | L28: 0.675 | M28: 223100 | N28: 200000 | O28: 200000 | P28: 765000 | Q28: 765000 | R28: 274.78448 | S28: 4980.026 | T28: 2784 | U28: 442900 | V28: 159.08764 | W28: 120000 | X28: 396150 | Y28: 516150 | Z28: 0.67470588 | AA28: 0.775 | AB28: 494005 | AC28: 44421 | AD28: 120000 | AE28: 396150 | AF28: 516150 | AG28: 0 | AH28: -22145 | AI28: 0.95 | AJ28: 0 | AK28: 22145 | AL28: 0 | AM28: 516150 | AO28: 516150 | AP28: 44587 | AQ28: 44606 | AR28: 44631 | AT28: 728571.43 | AU28: 36428.571 | AV28: 765000 | AX28: 88000 | AY28: 0.11503268 | AZ28: Ami Chandra & Manjula Chandra | BA28: 1 | BB28: 43869
B29: 129 North Bridges Bay, Langdon | C29: 2011558 | D29: 1 | E29: 43 | F29: Langdon | G29: Cost | H29: Pre-Sold | I29: Construction | J29: 0.5 | K29: 0.75 | L29: 0.65 | M29: 184000 | N29: 185000 | O29: 184000 | P29: 660000 | Q29: 657000 | R29: 310.78524 | S29: 8955 | T29: 2114 | U29: 405900 | V29: 192.00568 | W29: 92000 | X29: 335050 | Y29: 427050 | Z29: 0.65 | AA29: 0.72393626 | AB29: 220852.8 | AC29: 44470 | AD29: 92000 | AE29: 128852.8 | AF29: 220852.8 | AG29: 0 | AH29: 0 | AI29: 0.492 | AJ29: 0 | AK29: 206197.2 | AL29: 206197.2 | AM29: 220852.8 | AO29: 220852.8 | AP29: 44602 | AQ29: 44614 | AR29: 44638 | AT29: 625714.29 | AU29: 31285.714 | AV29: 657000 | AW29: 6938.62 | AX29: 37500 | AY29: 0.057077626 | AZ29: Sanjeev & Krishna Chavda | BA29: 0.99545455 | BB29: 44229 | BC29: Pre-sale purchaser mortgage financing approval letter has been obtained
B30: 85 Waterford Road | C30: 2110528 | D30: 2 | E30: 24 | F30: Chestermere | G30: Cost | H30: Pre-Sold | I30: Construction | J30: 0.6 | K30: 0.775 | L30: 0.675 | M30: 223100 | N30: 200000 | O30: 200000 | P30: 770000 | Q30: 765000 | R30: 271.85501 | S30: 4980.026 | T30: 2814 | U30: 449900 | V30: 159.87918 | W30: 120000 | X30: 396375 | Y30: 516375 | Z30: 0.675 | AA30: 0.7672734 | AB30: 426395 | AC30: 44421 | AD30: 120000 | AE30: 306395 | AF30: 426395 | AG30: 0 | AH30: 0 | AI30: 0.8 | AJ30: 0 | AK30: 89980 | AL30: 89980 | AM30: 426395 | AO30: 426395 | AP30: 44599 | AQ30: 44614 | AR30: 44638 | AT30: 728571.43 | AU30: 36428.571 | AV30: 765000 | AX30: 88000 | AY30: 0.11503268 | AZ30: Kamal Bulsara & Jotika Bulsara | BA30: 0.99350649 | BB30: 43869
B31: 12 Waterford Heights | C31: 2110528 | D31: 2 | E31: 12 | F31: Chestermere | G31: Cost | H31: Pre-Sold | I31: Construction | J31: 0.6 | K31: 0.775 | L31: 0.675 | M31: 218250 | N31: 250000 | O31: 218250 | P31: 780000 | Q31: 780000 | R31: 294.89603 | S31: 4919.1023 | T31: 2645 | U31: 429400 | V31: 162.34405 | W31: 130950 | X31: 370978.75 | Y31: 501928.75 | Z31: 0.6434984 | AA31: 0.775 | AB31: 368814.75 | AC31: 44421 | AD31: 130950 | AE31: 237864.75 | AF31: 368814.75 | AG31: 0 | AH31: 0 | AI31: 0.69 | AJ31: 0 | AK31: 133114 | AL31: 133114 | AM31: 368814.75 | AO31: 368814.75 | AP31: 44606 | AQ31: 44620 | AR31: 44650 | AT31: 742857.14 | AU31: 37142.857 | AV31: 780000 | AX31: 54390 | AY31: 0.069730769 | AZ31: Angrej Malhi | BA31: 1 | BB31: 44093
B32: 737 Marina Drive | C32: 1910205 | D32: 2 | E32: 4 | F32: Chestermere | G32: Cost | H32: Pre-Sold | I32: Construction | J32: 0.6 | K32: 0.775 | L32: 0.675 | M32: 205234 | N32: 175000 | O32: 175000 | P32: 750000 | Q32: 745465.25 | R32: 260.74335 | S32: 4899 | T32: 2859 | U32: 458100 | V32: 160.23085 | W32: 105000 | X32: 398189.04 | Y32: 503189.04 | Z32: 0.675 | AA32: 0.75857569 | AB32: 418440.54 | AC32: 44491 | AD32: 152117.28 | AE32: 266323.26 | AF32: 418440.54 | AG32: 0 | AH32: 0 | AI32: 0.815 | AJ32: 0 | AK32: 84748.5 | AL32: 84748.504 | AM32: 418440.54 | AO32: 418440.54 | AP32: 44627 | AQ32: 44636 | AR32: 44663 | AT32: 709966.9 | AU32: 35498.345 | AV32: 745465.25 | AW32: 23530.5 | AX32: 74550 | AY32: 0.10000466 | AZ32: Puneet & Yashwinder Matharoo | BA32: 0.99395367 | BB32: 44158
B33: 73 Waterford Road | C33: 2110528 | D33: 2 | E33: 21 | F33: Chestermere | G33: Cost | H33: Pre-Sold | I33: Construction | J33: 0.6 | K33: 0.775 | L33: 0.675 | M33: 220708 | N33: 200000 | O33: 200000 | P33: 765000 | Q33: 761783.4 | R33: 354.64777 | S33: 4972.9218 | T33: 2148 | U33: 445400 | V33: 207.35568 | W33: 120000 | X33: 394203.8 | Y33: 514203.8 | Z33: 0.675 | AA33: 0.77195259 | AB33: 337380 | AC33: 44421 | AD33: 120000 | AE33: 217380 | AF33: 337380 | AG33: 337380 | AH33: 0 | AI33: 0.603 | AJ33: 538755.39 | AK33: 176823.8 | AL33: 176823.8 | AM33: 337380 | AO33: 337380 | AP33: 44665 | AQ33: 44669 | AR33: 44697 | AT33: 725508 | AU33: 36275.4 | AV33: 761783.4 | AX33: 75000 | AY33: 0.098453182 | AZ33: Adam Virgo | BA33: 0.99579529 | BB33: 44111
B34: 8 Waterford Heights | C34: 2110528 | D34: 2 | E34: 13 | F34: Chestermere | G34: Cost | H34: Pre-Sold | I34: Construction | J34: 0.6 | K34: 0.775 | L34: 0.675 | M34: 207000 | N34: 250000 | O34: 207000 | P34: 735000 | Q34: 730364.25 | R34: 298.10786 | S34: 4888 | T34: 2450 | U34: 422200 | V34: 172.32653 | W34: 124200 | X34: 363430 | Y34: 487630 | Z34: 0.66765316 | AA34: 0.775 | AB34: 398968 | AC34: 44491 | AD34: 124200 | AE34: 274768 | AF34: 398968 | AG34: 0 | AH34: 0 | AI34: 0.79 | AJ34: 0 | AK34: 88662 | AL34: 88662 | AM34: 398968 | AO34: 398968 | AP34: 44677 | AQ34: 44683 | AR34: 44714 | AT34: 695585 | AU34: 34779.25 | AV34: 730364.25 | AW34: 4168.5 | AX34: 50000 | AY34: 0.068458992 | AZ34: Satbir Sidhu & Manjot Toor | BA34: 0.99369286 | BB34: 44214 | BC34: Pre-sale purchaser mortgage financing approval letter has been obtained
B35: 97 North Bridges Bay, Langdon | C35: 2011558 | D35: 1 | E35: 35 | F35: Langdon | G35: Cost | H35: Pre-Sold | I35: Construction | J35: 0.5 | K35: 0.75 | L35: 0.65 | M35: 184000 | N35: 185000 | O35: 184000 | P35: 695000 | Q35: 694773.45 | R35: 384.70291 | S35: 8860 | T35: 1806 | U35: 418900 | V35: 231.94906 | W35: 92000 | X35: 359602.74 | Y35: 451602.74 | Z35: 0.65 | AA35: 0.74905083 | AB35: 310852.34 | AC35: 44470 | AD35: 92000 | AE35: 218852.34 | AF35: 310852.34 | AG35: 0 | AH35: 0 | AI35: 0.664 | AJ35: 0 | AK35: 140750.4 | AL35: 140750.4 | AM35: 310852.34 | AO35: 310852.34 | AP35: 44671 | AQ35: 44686 | AR35: 44714 | AT35: 661689 | AU35: 33084.45 | AV35: 694773.45 | AW35: 3313 | AX35: 45000 | AY35: 0.064769314 | AZ35: Morgan & Christopher Shervey | BA35: 0.99967403 | BB35: 44283 | BC35: Grandfathered - Mortgage financing approval letter has also been received
B36: 113 North Bridges Bay, Langdon | C36: 2011558 | D36: 1 | E36: 39 | F36: Langdon | G36: Cost | H36: Pre-Sold | I36: Construction | J36: 0.5 | K36: 0.75 | L36: 0.65 | M36: 184000 | N36: 185000 | O36: 184000 | P36: 685000 | Q36: 682500 | R36: 259.21003 | S36: 8860 | T36: 2633 | U36: 437400 | V36: 166.12229 | W36: 92000 | X36: 351625 | Y36: 443625 | Z36: 0.65 | AA36: 0.71391213 | AB36: 334275 | AC36: 44470 | AD36: 92000 | AE36: 242275 | AF36: 334275 | AG36: 0 | AH36: 0 | AI36: 0.75 | AJ36: 0 | AK36: 109350 | AL36: 109350 | AM36: 334275 | AO36: 334275 | AP36: 44711 | AQ36: 44718 | AR36: 44748 | AT36: 650000 | AU36: 32500 | AV36: 682500 | AW36: 16625.35 | AX36: 35000 | AY36: 0.051282051 | AZ36: Dean Davies & Kimberley Davies | BA36: 0.99635036 | BB36: 44205 | BC36: Grandfathered - Mortgage financing approval letter has also been received
B37: 4 Waterford Heights | C37: 2110528 | D37: 2 | E37: 14 | F37: Chestermere | G37: Cost | H37: Pre-Sold | I37: Construction | J37: 0.6 | K37: 0.775 | L37: 0.675 | M37: 208800 | N37: 200000 | O37: 200000 | P37: 660000 | Q37: 650000 | R37: 258.65499 | S37: 5663 | T37: 2513 | U37: 363200 | V37: 144.52845 | W37: 120000 | X37: 318750 | Y37: 438750 | Z37: 0.675 | AA37: 0.76704545 | AB37: 362478 | AC37: 44582 | AD37: 120000 | AE37: 242478 | AF37: 362478 | AG37: 0 | AH37: 0 | AI37: 0.79 | AJ37: 0 | AK37: 76272 | AL37: 76272 | AM37: 362478 | AO37: 362478 | AP37: 44727 | AQ37: 44728 | AR37: 44761 | AT37: 619047.62 | AU37: 30952.381 | AV37: 650000 | AW37: 25972.64 | AX37: 32000 | AY37: 0.049230769 | AZ37: Kewal Saggu & Balbir Matharu | BA37: 0.98484848 | BB37: 44180 | BC37: Pre-sale purchaser mortgage financing pre-approval letter has been obtained
B38: 93 North Bridges Bay, Langdon | C38: 2011558 | D38: 1 | E38: 34 | F38: Langdon | G38: Cost | H38: Pre-Sold | I38: Construction | J38: 0.5 | K38: 0.75 | L38: 0.65 | M38: 184000 | N38: 185000 | O38: 184000 | P38: 760000 | Q38: 756750.75 | R38: 304.40497 | S38: 10193 | T38: 2486 | U38: 489900 | V38: 197.06356 | W38: 92000 | X38: 399887.99 | Y38: 491887.99 | Z38: 0.65 | AA38: 0.72991243 | AB38: 464453.59 | AC38: 44470 | AD38: 92000 | AE38: 372453.59 | AF38: 464453.59 | AG38: 0 | AH38: 0 | AI38: 0.944 | AJ38: 0 | AK38: 27434.4 | AL38: 27434.398 | AM38: 464453.59 | AO38: 464453.59 | AQ38: 44757 | AR38: 44781 | AT38: 720715 | AU38: 36035.75 | AV38: 756750.75 | AW38: 10672.75 | AX38: 75000 | AY38: 0.09910793 | AZ38: Mark & Carla Schwartz | BA38: 0.99572467 | BB38: 44277
B39: 78 Waterford Road | C39: 2110528 | D39: 6 | E39: 20 | F39: Chestermere | G39: Cost | H39: Pre-Sold | I39: Construction | J39: 0.6 | K39: 0.775 | L39: 0.675 | M39: 191250 | N39: 175000 | O39: 175000 | P39: 690000 | Q39: 686344.95 | R39: 226.74098 | S39: 5185 | T39: 3027 | U39: 463400 | V39: 153.08887 | W39: 105000 | X39: 358282.84 | Y39: 463282.84 | Z39: 0.675 | AA39: 0.7076802 | AB39: 407674.84 | AC39: 44582 | AD39: 105000 | AE39: 302674.84 | AF39: 407674.84 | AG39: 0 | AH39: 0 | AI39: 0.88 | AJ39: 0 | AK39: 55608 | AL39: 55608.001 | AM39: 407674.84 | AO39: 407674.84 | AP39: 44762 | AQ39: 44775 | AR39: 44802 | AT39: 653661.86 | AU39: 32683.093 | AV39: 686344.95 | AX39: 40000 | AY39: 0.058279732 | AZ39: Victor & Sheryl Vicente | BA39: 0.99470283 | BB39: 44178
B40: 101 North Bridges Bay, Langdon | C40: 2011558 | D40: 1 | E40: 36 | F40: Langdon | G40: Cost | H40: Pre-Sold | I40: Construction | J40: 0.5 | K40: 0.75 | L40: 0.65 | M40: 184000 | N40: 185000 | O40: 184000 | P40: 860000 | Q40: 855492.75 | R40: 473.69477 | S40: 8860 | T40: 1806 | U40: 542400 | V40: 300.33223 | W40: 92000 | X40: 428000 | Y40: 520000 | Z40: 0.60783683 | AA40: 0.71585903 | AB40: 384400 | AC40: 44470 | AD40: 92000 | AE40: 292400 | AF40: 384400 | AG40: 0 | AH40: 0 | AI40: 0.75 | AJ40: 0 | AK40: 135600 | AL40: 135600 | AM40: 384400 | AO40: 384400 | AQ40: 44776 | AR40: 44802 | AT40: 814755 | AU40: 40737.75 | AV40: 855492.75 | AW40: -5743.5 | AX40: 85500 | AY40: 0.099942402 | AZ40: Carole Campbell | BA40: 0.99475901 | BB40: 44287
B41: 81 Waterford Road | C41: 2110528 | D41: 2 | E41: 23 | F41: Chestermere | G41: Cost | H41: Pre-Sold | I41: Construction | J41: 0.6 | K41: 0.775 | L41: 0.675 | M41: 239900 | N41: 300000 | O41: 239900 | P41: 960000 | Q41: 801979.5 | R41: 310.60399 | S41: 5413.3806 | T41: 2582 | U41: 457400 | V41: 177.1495 | W41: 143940 | X41: 396060 | Y41: 540000 | Z41: 0.67333392 | AA41: 0.7744156 | AB41: 425650 | AC41: 44645 | AD41: 143940 | AE41: 281710 | AF41: 425650 | AG41: 0 | AH41: 0 | AI41: 0.75 | AJ41: 0 | AK41: 114350 | AL41: 114350 | AM41: 425650 | AO41: 425650 | AQ41: 44799 | AR41: 44827 | AT41: 763790 | AU41: 38189.5 | AV41: 801979.5 | AX41: 40000 | AY41: 0.049876587 | AZ41: Michelle Pickard & Brent Pickard | BA41: 0.83539531 | BB41: 44305 | BC41: Pre-sale purchaser mortgage financing pre-approval letter has been obtained
B42: 28 Waterford Heights | C42: 2110528 | D42: 2 | E42: 8 | F42: Chestermere | G42: Cost | H42: Pre-Sold | I42: Construction | J42: 0.6 | K42: 0.775 | L42: 0.675 | M42: 220708 | N42: 250000 | O42: 220708 | P42: 920000 | Q42: 910000 | R42: 313.68494 | S42: 4980 | T42: 2901 | U42: 531100 | V42: 183.0748 | W42: 132424.8 | X42: 407575.2 | Y42: 540000 | Z42: 0.59340659 | AA42: 0.71826849 | AB42: 449713 | AC42: 44491 | AD42: 132424.8 | AE42: 317288.2 | AF42: 449713 | AG42: 0 | AH42: 0 | AI42: 0.83 | AJ42: 0 | AK42: 90287 | AL42: 90287 | AM42: 449713 | AO42: 449713 | AQ42: 44802 | AR42: 44827 | AT42: 866666.67 | AU42: 43333.333 | AV42: 910000 | AX42: 86000 | AY42: 0.094505495 | AZ42: Sukhjinder Singh | BA42: 0.98913043 | BB42: 44233
B43: 89 North Bridges Bay, Langdon | C43: 2011558 | D43: 1 | E43: 33 | F43: Langdon | G43: Cost | H43: Pre-Sold | I43: Construction | J43: 0.5 | K43: 0.75 | L43: 0.65 | M43: 184000 | N43: 185000 | O43: 184000 | P43: 750000 | Q43: 750000 | R43: 255.18884 | S43: 8860 | T43: 2939 | U43: 590900 | V43: 201.05478 | W43: 92000 | X43: 395500 | Y43: 487500 | Z43: 0.65 | AA43: 0.62911343 | AB43: 212731.5 | AC43: 44470 | AD43: 92000 | AE43: 120731.5 | AF43: 212731.5 | AG43: 0 | AH43: 0 | AI43: 0.535 | AJ43: 0 | AK43: 274768.5 | AL43: 274768.5 | AM43: 212731.5 | AO43: 212731.5 | AQ43: 44803 | AR43: 44827 | AT43: 885637.85 | AU43: 44281.892 | AV43: 929919.74 | AX43: 94812 | AY43: 0.10195719 | AZ43: Robert & Jennifer Milne | BA43: 1.239893 | BB43: 44448 | BC43: Grandfathered - Deposit of $55K has been received to date. Remaining deposit of $40K to be received February 28, 2022. Total deposit per PSA is $92,991.90.
B44: 24 Waterford Heights | C44: 2110528 | D44: 2 | E44: 9 | F44: Chestermere | G44: Cost | H44: Pre-Sold | I44: Construction | J44: 0.6 | K44: 0.775 | L44: 0.675 | M44: 242500 | N44: 300000 | O44: 242500 | P44: 1060000 | Q44: 863520 | R44: 271.12088 | S44: 5413.3806 | T44: 3185 | U44: 572100 | V44: 179.62323 | W44: 145500 | X44: 394500 | Y44: 540000 | Z44: 0.62534742 | AA44: 0.66290204 | AB44: 336904.5 | AC44: 44645 | AD44: 145500 | AE44: 191404.5 | AF44: 336904.5 | AG44: 0 | AH44: 0 | AI44: 0.645 | AJ44: 0 | AK44: 203095.5 | AL44: 203095.5 | AM44: 336904.5 | AO44: 336904.5 | AP44: 44820 | AQ44: 44831 | AT44: 822400 | AU44: 41120 | AV44: 863520 | AX44: 80500 | AY44: 0.093223087 | AZ44: Balwinder Malhi | BA44: 0.81464151 | BB44: 44294
B45: 89 Waterford Road | C45: 2110528 | D45: 2 | E45: 25 | F45: Chestermere | G45: Cost | H45: Pre-Sold | I45: Construction | J45: 0.6 | K45: 0.775 | L45: 0.675 | M45: 223100 | N45: 300000 | O45: 223100 | P45: 950000 | Q45: 889899.99 | R45: 313.8977 | S45: 4980.026 | T45: 2835 | U45: 503400 | V45: 177.56614 | W45: 133860 | X45: 429177.5 | Y45: 563037.5 | Z45: 0.6326975 | AA45: 0.775 | AB45: 510180.5 | AC45: 44645 | AD45: 133860 | AE45: 353283 | AF45: 487143 | AG45: 0 | AH45: 23037.5 | AI45: 0.895 | AJ45: 0 | AK45: 52857 | AL45: 75894.5 | AM45: 487143 | AO45: 487143 | AP45: 44820 | AQ45: 44840 | AR45: 44865 | AT45: 847523.8 | AU45: 42376.19 | AV45: 889899.99 | AX45: 90000 | AY45: 0.10113496 | AZ45: Jaswinder Mann & Jaspal Kaur Mann | BA45: 0.93673683 | BB45: 44322
B46: 20 Waterford Heights | C46: 2110528 | D46: 2 | E46: 10 | F46: Chestermere | G46: Cost | H46: Pre-Sold | I46: Construction | J46: 0.6 | K46: 0.775 | L46: 0.675 | M46: 223100 | N46: 300000 | O46: 223100 | P46: 1070000 | Q46: 976002.3 | R46: 309.6454 | S46: 4980.026 | T46: 3152 | U46: 651100 | V46: 206.56726 | W46: 133860 | X46: 473640 | Y46: 607500 | Z46: 0.62243706 | AA46: 0.69492107 | AB46: 607500 | AC46: 44645 | AD46: 133860 | AE46: 473640 | AF46: 607500 | AG46: 0 | AH46: 0 | AI46: 1 | AJ46: 0 | AK46: 0 | AL46: 0 | AM46: 607500 | AO46: 607500 | AP46: 44949 | AQ46: 44959 | AR46: 44991 | AT46: 929526 | AU46: 46476.3 | AV46: 976002.3 | AX46: 120427.5 | AY46: 0.12338854 | AZ46: Murtatha Al-Saiedy | BA46: 0.91215168 | BB46: 44397
B47: 82 Waterford Road | C47: 2110528 | D47: 6 | E47: 21 | F47: Chestermere | G47: Cost | H47: Pre-Sold | I47: Construction | J47: 0.6 | K47: 0.775 | L47: 0.675 | M47: 191250 | N47: 300000 | O47: 191250 | P47: 785000 | Q47: 700000 | R47: 291.54519 | S47: 5184.5401 | T47: 2401 | U47: 423100 | V47: 176.21824 | W47: 114750 | X47: 357750 | Y47: 472500 | Z47: 0.675 | AA47: 0.76910556 | AB47: 375187 | AC47: 44645 | AD47: 114750 | AE47: 260437 | AF47: 375187 | AG47: 0 | AH47: 0 | AI47: 0.77 | AJ47: 0 | AK47: 97313 | AL47: 97313 | AM47: 375187 | AO47: 375187 | AP47: 44949 | AQ47: 44960 | AT47: 666666.67 | AU47: 33333.333 | AV47: 700000 | AX47: 69000 | AY47: 0.098571429 | AZ47: Ajminder Kaur | BA47: 0.89171975 | BB47: 44481
B48: 125 Spear Grass Close, Carseland | C48: 0711421 | D48: 10 | E48: 7 | F48: Rural Alberta | G48: Cost | H48: Pre-Sold | I48: Construction | J48: 0.5 | K48: 0.725 | L48: 0.625 | M48: 85000 | N48: 85000 | O48: 85000 | P48: 605000 | Q48: 605000 | R48: 344.72934 | S48: 9314 | T48: 1755 | U48: 491900 | V48: 280.2849 | W48: 42500 | X48: 332500 | Y48: 375000 | Z48: 0.61983471 | AA48: 0.650026 | AB48: 345486 | AC48: 44470 | AD48: 42500 | AE48: 302986 | AF48: 345486 | AG48: 0 | AH48: 0 | AI48: 0.94 | AJ48: 0 | AK48: 29514 | AL48: 29514 | AM48: 345486 | AO48: 345486 | AP48: 44973 | AQ48: 44980 | AR48: 45014 | AT48: 576200 | AU48: 28810 | AV48: 605010 | AW48: 46616.88 | AX48: 60501 | AY48: 0.1 | AZ48: Bonnie & Roy Klatzel | BA48: 1.0000165 | BB48: 44266
B49: 16 Waterford Heights | C49: 2110528 | D49: 2 | E49: 11 | F49: Chestermere | G49: Cost | H49: Pre-Sold | I49: Construction | J49: 0.6 | K49: 0.775 | L49: 0.675 | M49: 223100 | N49: 300000 | O49: 223100 | P49: 1050000 | Q49: 952776.25 | R49: 313.10426 | S49: 4980.026 | T49: 3043 | U49: 652100 | V49: 214.2951 | W49: 133860 | X49: 473640 | Y49: 607500 | Z49: 0.63761035 | AA49: 0.69412706 | AB49: 574895 | AC49: 44645 | AD49: 133860 | AE49: 441035 | AF49: 574895 | AG49: 0 | AH49: 0 | AI49: 0.95 | AJ49: 0 | AK49: 32605 | AL49: 32605 | AM49: 574895 | AO49: 574895 | AP49: 44985 | AQ49: 44986 | AR49: 45019 | AT49: 907405.95 | AU49: 45370.298 | AV49: 952776.25 | AX49: 100000 | AY49: 0.10495644 | AZ49: Tamer Hammoud and Lamia Akl | BA49: 0.90740595 | BB49: 44546
B50: 36 Waterford Heights | C50: 2110528 | D50: 2 | E50: 6 | F50: Chestermere | G50: Cost | H50: Pre-Sold | I50: Construction | J50: 0.6 | K50: 0.775 | L50: 0.675 | M50: 239900 | N50: 250000 | O50: 239900 | P50: 860000 | Q50: 849999.99 | R50: 276.3329 | S50: 5413 | T50: 3076 | U50: 435000 | V50: 141.41743 | W50: 143940 | X50: 379107.5 | Y50: 523047.5 | Z50: 0.61535001 | AA50: 0.775 | AB50: 496947.5 | AC50: 44582 | AD50: 143940 | AE50: 353007.5 | AF50: 496947.5 | AG50: 0 | AH50: 0 | AI50: 0.94 | AJ50: 0 | AK50: 26100 | AL50: 26100 | AM50: 496947.5 | AO50: 496947.5 | AP50: 45022 | AQ50: 45029 | AT50: 809523.8 | AU50: 40476.19 | AV50: 849999.99 | AX50: 85000 | AY50: 0.1 | AZ50: Harpritt Sohi & Mandip Sohi | BA50: 0.98837208 | BB50: 44168
B51: 57 Waterford Road | C51: 2110528 | D51: 2 | E51: 17 | F51: Chestermere | G51: Cost | H51: Pre-Sold | I51: Construction | J51: 0.6 | K51: 0.775 | L51: 0.675 | M51: 218250 | N51: 300000 | O51: 218250 | P51: 990000 | Q51: 968210.25 | R51: 307.07588 | S51: 4886.8106 | T51: 3153 | U51: 537600 | V51: 170.50428 | W51: 130950 | X51: 454833.75 | Y51: 585783.75 | Z51: 0.60501709 | AA51: 0.775 | AB51: 545463.75 | AC51: 44645 | AD51: 130950 | AE51: 414513.75 | AF51: 545463.75 | AG51: 0 | AH51: 0 | AI51: 0.925 | AJ51: 0 | AK51: 40320 | AL51: 40320 | AM51: 545463.75 | AO51: 545463.75 | AP51: 45063 | AQ51: 45089 | AR51: 45117 | AT51: 922105 | AU51: 46105.25 | AV51: 968210.25 | AX51: 80410.51 | AY51: 0.08305067 | AZ51: Aftab Shah & Urooj Sheikh | BA51: 0.97799015 | BB51: 44506
B52: 65 Waterford Road | C52: 2110528 | D52: 2 | E52: 19 | F52: Chestermere | G52: Cost | H52: Pre-Sold | I52: Construction | J52: 0.6 | K52: 0.775 | L52: 0.675 | M52: 215910 | N52: 300000 | O52: 215910 | P52: 990000 | Q52: 940825.2 | R52: 296.41626 | S52: 4898.328 | T52: 3174 | U52: 531600 | V52: 167.48582 | W52: 129546 | X52: 449774.25 | Y52: 579320.25 | Z52: 0.61575758 | AA52: 0.775 | AB52: 579320.25 | AC52: 44645 | AD52: 129546 | AE52: 449774.25 | AF52: 579320.25 | AG52: 0 | AH52: 0 | AI52: 1 | AJ52: 0 | AK52: 0 | AL52: 0 | AM52: 579320.25 | AO52: 579320.25 | AP52: 45089 | AQ52: 45096 | AR52: 45131 | AT52: 896024 | AU52: 44801.2 | AV52: 940825.2 | AX52: 185000 | AY52: 0.19663589 | AZ52: Kulwant Nijjar and Manjit Nijjar | BA52: 0.95032848 | BB52: 44507
B53: 33 Waterford Terrace, Chestermere | C53: 2210618 | D53: 2 | E53: 31 | F53: Chestermere | G53: Cost | H53: Pre-Sold | I53: Construction | J53: 0.6 | K53: 0.775 | L53: 0.675 | M53: 245000 | N53: 300000 | O53: 245000 | P53: 915000 | Q53: 906885 | R53: 322.73488 | S53: 4886.8106 | T53: 2810 | U53: 507600 | V53: 180.64057 | W53: 147000 | X53: 436265 | Y53: 583265 | Z53: 0.64315211 | AA53: 0.775 | AB53: 532505 | AC53: 44886 | AD53: 147000 | AE53: 385505 | AF53: 532505 | AG53: 0 | AH53: 0 | AI53: 0.9 | AJ53: 0 | AK53: 50760 | AL53: 50760 | AM53: 532505 | AO53: 532505 | AP53: 45097 | AQ53: 45103 | AR53: 45131 | AT53: 863700 | AU53: 43185 | AV53: 906885 | AX53: 45350 | AY53: 0.05000634 | AZ53: Ravinder Pelia & Kirandeep Khasria | BA53: 0.99113115 | BB53: 44511 | BC53: Received mortgage financing pre-approval letter from RBC for borrower dated October 10, 2022
B54: 168 Sandpiper Landing, Chestermere | C54: 2012107 | D54: 8 | E54: 9 | F54: Chestermere | G54: Cost | H54: Pre-Sold | I54: Construction | J54: 0.6 | K54: 0.775 | L54: 0.675 | M54: 232900 | N54: 275000 | O54: 232900 | P54: 900000 | Q54: 895156.5 | R54: 358.34928 | S54: 5620.9086 | T54: 2498 | U54: 509900 | V54: 204.1233 | W54: 139740 | X54: 435930 | Y54: 575670 | Z54: 0.64309425 | AA54: 0.775 | AB54: 463492 | AC54: 44939 | AD54: 139740 | AE54: 323752 | AF54: 463492 | AG54: 0 | AH54: 0 | AI54: 0.78 | AJ54: 0 | AK54: 112178 | AL54: 112178 | AM54: 463492 | AO54: 463492 | AP54: 45098 | AQ54: 45107 | AR54: 45131 | AT54: 852530 | AU54: 42626.5 | AV54: 895156.5 | AX54: 88547.66 | AY54: 0.098918636 | AZ54: Narinder Singh & Satwant Kaur | BA54: 0.99461833 | BB54: 44553
B55: 41 Waterford Terrace, Chestermere | C55: 2210618 | D55: 2 | E55: 33 | F55: Chestermere | G55: Cost | H55: Pre-Sold | I55: Construction | J55: 0.6 | K55: 0.775 | L55: 0.675 | M55: 272000 | N55: 300000 | O55: 272000 | P55: 960000 | Q55: 954975 | R55: 303.93857 | S55: 5413.1653 | T55: 3142 | U55: 540600 | V55: 172.05602 | W55: 163200 | X55: 444300 | Y55: 607500 | Z55: 0.63614231 | AA55: 0.7476003 | AB55: 580470 | AC55: 44886 | AD55: 163200 | AE55: 417270 | AF55: 580470 | AG55: 0 | AH55: 0 | AI55: 0.95 | AJ55: 0 | AK55: 27030 | AL55: 27030 | AM55: 580470 | AO55: 580470 | AP55: 45099 | AQ55: 45113 | AR55: 45147 | AT55: 909500 | AU55: 45475 | AV55: 954975 | AX55: 89412.49 | AY55: 0.093628095 | AZ55: Simranjit Singh Sidhu | BA55: 0.99476562 | BB55: 44511
B56: 72 Waterford Terrace, Chestermere | C56: 2210618 | D56: 7 | E56: 14 | F56: Chestermere | G56: Cost | H56: Pre-Sold | I56: Construction | J56: 0.6 | K56: 0.775 | L56: 0.675 | M56: 248000 | N56: 275000 | O56: 248000 | P56: 915000 | Q56: 908145 | R56: 319.54433 | S56: 5872.7838 | T56: 2842 | U56: 517100 | V56: 181.94933 | W56: 148800 | X56: 444152.5 | Y56: 592952.5 | Z56: 0.65292712 | AA56: 0.775 | AB56: 567097.5 | AC56: 44886 | AD56: 148800 | AE56: 418297.5 | AF56: 567097.5 | AG56: 0 | AH56: 0 | AI56: 0.95 | AJ56: 0 | AK56: 25855 | AL56: 25855 | AM56: 567097.5 | AO56: 567097.5 | AP56: 45131 | AQ56: 45135 | AT56: 864900 | AU56: 43245 | AV56: 908145 | AX56: 95380 | AY56: 0.10502728 | AZ56: Gagandeep Kaur Mann | BA56: 0.9925082 | BB56: 44511
B57: 32 Vantage Drive, Cochrane | C57: 2211425 | D57: 6 | E57: 8 | F57: Cochrane | G57: Cost | H57: Speculative | I57: Construction | J57: 0.5 | K57: 0.725 | L57: 0.625 | M57: 155000 | N57: 250000 | O57: 155000 | P57: 685000 | Q57: 685000 | R57: 301.36384 | S57: 3942 | T57: 2273 | U57: 399400 | V57: 175.71491 | W57: 77500 | X57: 324440 | Y57: 401940 | Z57: 0.58677372 | AA57: 0.725 | AB57: 385964 | AC57: 44991 | AD57: 77500 | AE57: 308464 | AF57: 385964 | AG57: 0 | AH57: 0 | AI57: 0.96 | AJ57: 0 | AK57: 15976 | AL57: 15976 | AM57: 385964 | AO57: 385964 | AP57: 45251 | AQ57: 45258 | AT57: 687619.05 | AU57: 34380.952 | AV57: 722000 | AX57: 30000 | AY57: 0.041551247 | AZ57: Jonah Gilham and Zoe Stein | BA57: 1.0540146 | BB57: 45223
B58: 73 North Bridges Bay, Langdon | C58: 2011558 | D58: 1 | E58: 29 | F58: Langdon | G58: Cost | H58: Pre-Sold | I58: Construction | J58: 0.6 | K58: 0.775 | L58: 0.675 | M58: 184000 | N58: 215000 | O58: 184000 | P58: 840000 | Q58: 840000 | R58: 266.41294 | S58: 8859 | T58: 3153 | U58: 548600 | V58: 173.99302 | W58: 110400 | X58: 456600 | Y58: 567000 | Z58: 0.675 | AA58: 0.77395577 | AB58: 545056 | AC58: 44981 | AD58: 110400 | AE58: 434656 | AF58: 545056 | AG58: 0 | AH58: 0 | AI58: 0.96 | AJ58: 0 | AK58: 21944 | AL58: 21944 | AM58: 545056 | AO58: 545056 | AP58: 45254 | AQ58: 45261 | AT58: 944450 | AU58: 47222.5 | AV58: 991672.5 | AX58: 89445 | AY58: 0.090196108 | AZ58: Chris Brown & Kimberly McLellan | BA58: 1.1805625 | BB58: 44674

Sheet Sheet2
B3: Civic Address | C3: Plan / Condominium Plan | D3: Block/Unit | E3: Lot | F3: Geographical Region | G3: % Complete / Cost to Complete ("%" or "Cost") | H3: Financing Category (Presold vs Speculative) | I3: Project Phase (Land, Construction, Completed) | J3: Land - Pledged LTC | K3: Const. - Pledged LTC | L3: Const. - Pledged LTV | M3: Land Cost | N3: "As Is" Value - Fully Serviced Lots - Appraised | O3: Land Value: Lesser of Cost and Appraised Value | P3: "As Complete" Appraised Value | Q3: "As Complete" Value - for LTV | R3: $Value/SQFT | S3: Lot Size (SF) | T3: Unit Size (SF AG - "as if" built) | U3: Construction Costs (Excl. Land) | V3: $Const. /SQFT | W3: Land Financing | X3: Construction Financing | Y3: Total Committed | Z3: LTV - Committed | AA3: Overall LTC - Committed | AB3: Possible Draw Amount | AC3: Initial Draw Date | AD3: Land Draw | AE3: Construction Draw | AF3: Total Amount Drawn | AG3: Net Loan Amount | AH3: Available Draw Amount | AI3: Percent Complete | AJ3: Security Value | AK3: Cost to Complete | AL3: Unfunded | AM3: Gross Amount Received | AN3: Pre-Payment Penalty | AO3: Net Paydown Amount | AP3: Payout Statement Date | AQ3: Date Funds Received | AR3: Date Discharge Sent | AS3: Notes | AT3: Price | AU3: GST | AV3: Full Price | AW3: Change Orders | AX3: Deposit | AY3: Deposit Percentage of Purchase Price | AZ3: Purchaser | BA3: Sale Price - Appraised | BB3: Sale Date | BC3: Notes
B4: 232 Aspenmere Way, Chestermere | C4: 1513280 | D4: 42 | E4: 57 | F4: Chestermere | G4: Cost | H4: Pre-Sold | I4: =IF(AI4=0,"Land",IF(AND(AI4>0,AI4<1),"Construction",IF(AI4=1,"Completed"))) -> Construction | J4: 0.55 | K4: 0.75 | L4: 0.65 | M4: 200000 | N4: 210000 | O4: =MIN(M4:N4) -> 200000 | P4: 740000 | Q4: =IF(AV4>0,MIN(P4,AV4),P4) -> 739000 | R4: =Q4/T4 -> 228.50959 | S4: 8309.7308 | T4: 3234 | U4: 426200 | V4: =U4/T4 -> 131.78726 | W4: =J4*MIN(M4:N4) -> 110000 | X4: =MAX(IF(Q4="",0,MIN(((U4+M4)*K4)-W4,(Q4*L4)-W4)),0) -> 359650 | Y4: =W4+X4 -> 469650 | Z4: =IF(Q4>0,Y4/Q4,Y4/N4) -> 0.63552097 | AA4: =IF(Q4>0,Y4/(M4+U4),Y4/M4) -> 0.75 | AB4: =ROUND(IF(Q4>0,IF(G4="%",W4+X4*AI4,W4+MAX((O4+(U4*AI4))-(O4+U4-X4),0)),W4),2) -> 459847.4 | AC4: 44008 | AD4: 110000 | AE4: =243297.4+32817.4+53275 -> 329389.8 | AF4: =SUM(AD4:AE4) -> 439389.8 | AG4: =AF4-AO4 -> 0 | AH4: =AB4-AF4 -> 20457.6 | AI4: 0.977 | AJ4: =IF(AM4>0,0,N4+(Q4-N4)*AI4) -> 0 | AK4: =(1-AI4)*U4 -> 9802.6 | AL4: =Y4-AF4 -> 30260.2 | AM4: 439389.8 | AO4: =AM4-AN4 -> 439389.8 | AP4: 44069 | AQ4: 44074 | AR4: 44097 | AT4: =AV4/1.05 -> 703809.52 | AU4: =AT4*0.05 -> 35190.476 | AV4: 739000 | AX4: 70000 | AY4: =AX4/AV4 -> 0.094722598 | AZ4: Louis M Yhap & Bibi S Yhap | BA4: =IFERROR(AV4/Q4,0) -> 1 | BB4: 43800
B5: 728 Marina Drive, Chestermere | C5: 1910205 | D5: 1 | E5: 2 | F5: Chestermere | G5: Cost | H5: Pre-Sold | I5: =IF(AI5=0,"Land",IF(AND(AI5>0,AI5<1),"Construction",IF(AI5=1,"Completed"))) -> Construction | J5: 0.55 | K5: 0.75 | L5: 0.65 | M5: 204389 | N5: 180000 | O5: =MIN(M5:N5) -> 180000 | P5: 705000 | Q5: =IF(AV5>0,MIN(P5,AV5),P5) -> 698500 | R5: =Q5/T5 -> 230.83278 | S5: =489*10.7639 -> 5263.5471 | T5: 3026 | U5: 400200 | V5: =U5/T5 -> 132.2538 | W5: =J5*MIN(M5:N5) -> 99000 | X5: =MAX(IF(Q5="",0,MIN(((U5+M5)*K5)-W5,(Q5*L5)-W5)),0) -> 354441.75 | Y5: =W5+X5 -> 453441.75 | Z5: =IF(Q5>0,Y5/Q5,Y5/N5) -> 0.649165 | AA5: =IF(Q5>0,Y5/(M5+U5),Y5/M5) -> 0.75 | AB5: =ROUND(IF(Q5>0,IF(G5="%",W5+X5*AI5,W5+MAX((O5+U5*AI5)-(O5+U5-X5),0)),W5),2) -> 346988.55 | AC5: 44008 | AD5: 99000 | AE5: =155142.15+17608.8+54827.4+9604.8+10805.4 -> 247988.55 | AF5: =SUM(AD5:AE5) -> 346988.55 | AG5: =AF5-AO5 -> 0 | AH5: =AB5-AF5 -> 0 | AI5: 0.734 | AJ5: =IF(AM5>0,0,O5+(Q5-O5)*AI5) -> 0 | AK5: =(1-AI5)*U5 -> 106453.2 | AL5: =Y5-AF5 -> 106453.2 | AM5: 346988.55 | AO5: =AM5-AN5 -> 346988.55 | AP5: 44102 | AQ5: 44109 | AR5: 44134 | AT5: =AV5/1.05 -> 665238.1 | AU5: =AT5*0.05 -> 33261.905 | AV5: 698500 | AX5: 70000 | AY5: =AX5/AV5 -> 0.10021475 | AZ5: Sukhjeet Singh & Rajandeep Kaur Sandhu | BA5: =IFERROR(AV5/Q5,0) -> 1 | BB5: 43807
B6: 732 Marina Drive | C6: 1910205 | D6: 1 | E6: 3 | F6: Chestermere | G6: Cost | H6: Pre-Sold | I6: =IF(AI6=0,"Land",IF(AND(AI6>0,AI6<1),"Construction",IF(AI6=1,"Completed"))) -> Construction | J6: 0.55 | K6: 0.75 | L6: 0.65 | M6: 204389 | N6: 175000 | O6: =MIN(M6:N6) -> 175000 | P6: 655000 | Q6: =IF(AV6>0,MIN(P6,AV6),P6) -> 648375 | R6: =Q6/T6 -> 251.99184 | S6: 5285 | T6: 2573 | U6: 331300 | V6: =U6/T6 -> 128.7602 | W6: =J6*MIN(M6:N6) -> 96250 | X6: =MAX(IF(Q6="",0,MIN(((U6+M6)*K6)-W6,(Q6*L6)-W6)),0) -> 305516.75 | Y6: =W6+X6 -> 401766.75 | Z6: =IF(Q6>0,Y6/Q6,Y6/N6) -> 0.61965182 | AA6: =IF(Q6>0,Y6/(M6+U6),Y6/M6) -> 0.75 | AB6: =ROUND(IF(Q6>0,IF(G6="%",W6+X6*AI6,W6+MAX((O6+U6*AI6)-(O6+U6-X6),0)),W6),2) -> 315297.45 | AC6: 44068 | AD6: 96250 | AE6: =130921.65+41412.5+46713.3 -> 219047.45 | AF6: =SUM(AD6:AE6) -> 315297.45 | AG6: =AF6-AO6 -> 0 | AH6: =AB6-AF6 -> 0 | AI6: 0.739 | AJ6: =IF(AM6>0,0,O6+(Q6-O6)*AI6) -> 0 | AK6: =(1-AI6)*U6 -> 86469.3 | AL6: =Y6-AF6 -> 86469.3 | AM6: =315294.45+3 -> 315297.45 | AO6: =AM6-AN6 -> 315297.45 | AP6: 44111 | AQ6: 44123 | AR6: 44151 | AT6: =AV6/1.05 -> 617500 | AU6: =AV6-AT6 -> 30875 | AV6: 648375 | AX6: 65000 | AY6: =AX6/AV6 -> 0.10025063 | AZ6: Dalwinder Bassi and Baljiit Bassi | BA6: =AV6/P6 -> 0.9898855 | BB6: 43845
B7: 296 Aspenmere Way, Chestermere | C7: 1513280 | D7: 42 | E7: 73 | F7: Chestermere | G7: Cost | H7: Pre-Sold | I7: =IF(AI7=0,"Land",IF(AND(AI7>0,AI7<1),"Construction",IF(AI7=1,"Completed"))) -> Construction | J7: 0.55 | K7: 0.75 | L7: 0.65 | M7: 205000 | N7: 190000 | O7: =MIN(M7:N7) -> 190000 | P7: 730000 | Q7: =IF(AV7>0,MIN(P7,AV7),P7) -> 730000 | R7: =Q7/T7 -> 226.91949 | S7: 5812.506 | T7: 3217 | U7: 395600 | V7: =U7/T7 -> 122.97171 | W7: =J7*MIN(M7:N7) -> 104500 | X7: =MAX(IF(Q7="",0,MIN(((U7+M7)*K7)-W7,(Q7*L7)-W7)),0) -> 345950 | Y7: =W7+X7 -> 450450 | Z7: =IF(Q7>0,Y7/Q7,Y7/N7) -> 0.61705479 | AA7: =IF(Q7>0,Y7/(M7+U7),Y7/M7) -> 0.75 | AB7: =ROUND(IF(Q7>0,IF(G7="%",W7+X7*AI7,W7+MAX((O7+U7*AI7)-(O7+U7-X7),0)),W7),2) -> 362626.8 | AC7: 44008 | AD7: 104500 | AE7: =22349.2+54197.2+49845.6+46285.2+53801.6+31648 -> 258126.8 | AF7: =SUM(AD7:AE7) -> 362626.8 | AG7: =AF7-AO7 -> 0 | AH7: =AB7-AF7 -> 0 | AI7: 0.778 | AJ7: =IF(AM7>0,0,O7+(Q7-O7)*AI7) -> 0 | AK7: =(1-AI7)*U7 -> 87823.2 | AL7: =Y7-AF7 -> 87823.2 | AM7: 362626.8 | AN7: 0 | AO7: =AM7-AN7 -> 362626.8 | AQ7: 44130 | AR7: 44162 | AT7: =AV7/1.05 -> 695238.1 | AU7: =AT7*0.05 -> 34761.905 | AV7: 730000 | AX7: 50000 | AY7: =AX7/AV7 -> 0.068493151 | AZ7: Arshdeep Singh Badesha & Navkiran Kaur Badesha | BA7: =IFERROR(AV7/Q7,0) -> 1 | BB7: 43797
B8: 736 Marina Drive | C8: 1910205 | D8: 1 | E8: 4 | F8: Chestermere | G8: Cost | H8: Pre-Sold | I8: =IF(AI8=0,"Land",IF(AND(AI8>0,AI8<1),"Construction",IF(AI8=1,"Completed"))) -> Construction | J8: 0.55 | K8: 0.75 | L8: 0.65 | M8: 204389 | N8: 180000 | O8: =MIN(M8:N8) -> 180000 | P8: 625000 | Q8: =IF(AV69>0,MIN(P8,AV69),P8) -> 625000 | R8: =Q8/T8 -> 255.41479 | S8: 5264 | T8: 2447 | U8: 304700 | V8: =U8/T8 -> 124.51982 | W8: =J8*MIN(M8:N8) -> 99000 | X8: =MAX(IF(Q8="",0,MIN(((U8+M8)*K8)-W8,(Q8*L8)-W8)),0) -> 282816.75 | Y8: =W8+X8 -> 381816.75 | Z8: =IF(Q8>0,Y8/Q8,Y8/N8) -> 0.6109068 | AA8: =IF(Q8>0,Y8/(M8+U8),Y8/M8) -> 0.75 | AB8: =ROUND(IF(Q8>0,IF(G8="%",W8+X8*AI8,W8+MAX((O8+U8*AI8)-(O8+U8-X8),0)),W8),2) -> 283703.35 | AC8: 44068 | AD8: 99000 | AE8: =100910.85+29555.9+54236.6 -> 184703.35 | AF8: =SUM(AD8:AE8) -> 283703.35 | AG8: =AF8-AO8 -> 0 | AH8: =AB8-AF8 -> 0 | AI8: 0.678 | AJ8: =IF(AM8>0,0,O8+(Q8-O8)*AI8) -> 0 | AK8: =(1-AI8)*U8 -> 98113.4 | AL8: =Y8-AF8 -> 98113.4 | AM8: 283703.35 | AO8: =AM8-AN8 -> 283703.35 | AP8: 44111 | AQ8: 44137 | AR8: 44162 | AT8: =AV8/1.05 -> 595238.1 | AU8: =AV8-AT8 -> 29761.905 | AV8: 625000 | AX8: =25000+31250+100000 -> 156250 | AY8: =AX8/AV8 -> 0.25 | AZ8: Jobandeep Singh Gill & Amandeep Kaur Gill | BA8: =IFERROR(AV8/P8,0) -> 1 | BB8: 43801
B9: 741 Marina Drive, Chestermere | C9: 1910205 | D9: 2 | E9: 5 | F9: Chestermere | G9: Cost | H9: Pre-sold | I9: =IF(AI9=0,"Land",IF(AND(AI9>0,AI9<1),"Construction",IF(AI9=1,"Completed"))) -> Completed | J9: 0.55 | K9: 0.75 | L9: 0.65 | M9: 214757 | N9: 175000 | O9: =MIN(M9:N9) -> 175000 | P9: 622000 | Q9: =IF(AV9>0,MIN(P9,AV9),P9) -> 622000 | R9: =Q9/T9 -> 256.60066 | S9: =464*10.7639 -> 4994.4496 | T9: 2424 | U9: 373978.81 | V9: =U9/T9 -> 154.28169 | W9: =J9*MIN(M9:N9) -> 96250 | X9: =MAX(IF(Q9="",0,MIN(((U9+M9)*K9)-W9,(Q9*L9)-W9)),0) -> 308050 | Y9: =W9+X9 -> 404300 | Z9: =IF(Q9>0,Y9/Q9,Y9/N9) -> 0.65 | AA9: =IF(Q9>0,Y9/(M9+U9),Y9/M9) -> 0.68672568 | AB9: =ROUND(IF(Q9>0,IF(G9="%",W9+X9*AI9,W9+MAX((O9+U9*AI9)-(O9+U9-X9),0)),W9),2) -> 404300 | AC9: 44008 | AD9: 87500 | AE9: =285700+23532.5+23117.5 -> 332350 | AF9: =SUM(AD9:AE9) -> 419850 | AG9: =AF9-AO9 -> 0 | AH9: =AB9-AF9 -> -15550 | AI9: 1 | AJ9: =IF(AM9>0,0,O9+(Q9-O9)*AI9) -> 0 | AK9: =(1-AI9)*U9 -> 0 | AL9: =Y9-AF9 -> -15550 | AM9: 419850 | AO9: =AM9-AN9 -> 419850 | AP9: 44174 | AQ9: 44180 | AR9: 44211 | AT9: =AV9/1.05 -> 600000 | AU9: =AT9*0.05 -> 30000 | AV9: 630000 | AX9: 63000 | AY9: =AX9/AV9 -> 0.1 | AZ9: Avtar Sidhu & Jasvir Sidhu | BA9: =IFERROR(AV9/P9,0) -> 1.0128617 | BB9: 44077
B10: 729 Marina Drive | C10: 1910205 | D10: 2 | E10: 2 | F10: Chestermere | G10: Cost | H10: Pre-Sold | I10: =IF(AI10=0,"Land",IF(AND(AI10>0,AI10<1),"Construction",IF(AI10=1,"Completed"))) -> Construction | J10: 0.6 | K10: 0.775 | L10: 0.675 | M10: 205234 | N10: 180000 | O10: =MIN(M10:N10) -> 180000 | P10: 668000 | Q10: =IF(AV10>0,MIN(P10,AV10),P10) -> 665000 | R10: =Q10/T10 -> 221.44522 | S10: 4897 | T10: 3003 | U10: 375400 | V10: =U10/T10 -> 125.00833 | W10: =J10*MIN(M10:N10) -> 108000 | X10: =MAX(IF(Q10="",0,MIN(((U10+M10)*K10)-W10,(Q10*L10)-W10)),0) -> 340875 | Y10: =W10+X10 -> 448875 | Z10: =IF(Q10>0,Y10/Q10,Y10/N10) -> 0.675 | AA10: =IF(Q10>0,Y10/(M10+U10),Y10/M10) -> 0.77307736 | AB10: =ROUND(IF(Q10>0,IF(G10="%",W10+X10*AI10,W10+MAX((O10+U10*AI10)-(O10+U10-X10),0)),W10),2) -> 416590.6 | AC10: 44154 | AD10: 108000 | AE10: =143039.2+70199.8+95351.6 -> 308590.6 | AF10: =SUM(AD10:AE10) -> 416590.6 | AG10: =AF10-AO10 -> 0 | AH10: =AB10-AF10 -> 0 | AI10: 0.914 | AJ10: =IF(AM10>0,0,O10+(Q10-O10)*AI10) -> 0 | AK10: =(1-AI10)*U10 -> 32284.4 | AL10: =Y10-AF10 -> 32284.4 | AM10: 416590.6 | AO10: =AM10-AN10 -> 416590.6 | AP10: 44223 | AQ10: 44228 | AT10: =AV10/1.05 -> 633333.33 | AU10: =AT10*0.05 -> 31666.667 | AV10: 665000 | AX10: =5000+94750 -> 99750 | AY10: =AX10/AV10 -> 0.15 | AZ10: Gurvir Sidhu | BA10: =IFERROR(AV10/P10,0) -> 0.99550898 | BB10: 44037
B11: 744 Marina Drive | C11: 1910205 | D11: 1 | E11: 6 | F11: Chestermere | G11: Cost | H11: Speculative | I11: =IF(AI11=0,"Land",IF(AND(AI11>0,AI11<1),"Construction",IF(AI11=1,"Completed"))) -> Construction | J11: 0.5 | K11: 0.725 | L11: 0.625 | M11: 211331 | N11: 200000 | O11: =MIN(M11:N11) -> 200000 | P11: 585000 | Q11: =IF(AV11>0,MIN(P11,AV11),P11) -> 585000 | R11: =Q11/T11 -> 253.68604 | S11: 5242 | T11: 2306 | U11: 318700 | V11: =U11/T11 -> 138.20468 | W11: =J11*MIN(M11:N11) -> 100000 | X11: =MAX(IF(Q11="",0,MIN(((U11+M11)*K11)-W11,(Q11*L11)-W11)),0) -> 265625 | Y11: =W11+X11 -> 365625 | Z11: =IF(Q11>0,Y11/Q11,Y11/N11) -> 0.625 | AA11: =IF(Q11>0,Y11/(M11+U11),Y11/M11) -> 0.68981814 | AB11: =ROUND(IF(Q11>0,IF(G11="%",W11+X11*AI11,W11+MAX((O11+U11*AI11)-(O11+U11-X11),0)),W11),2) -> 361800.6 | AC11: 44154 | AD11: 100000 | AE11: =180850.8+84774.2 -> 265625 | AF11: =SUM(AD11:AE11) -> 365625 | AG11: =AF11-AO11 -> 0 | AH11: =AB11-AF11 -> -3824.4 | AI11: 0.988 | AJ11: =IF(AM11>0,0,O11+(Q11-O11)*AI11) -> 0 | AK11: =(1-AI11)*U11 -> 3824.4 | AL11: =Y11-AF11 -> 0 | AM11: 365625 | AO11: =AM11-AN11 -> 365625 | AP11: 44236 | AQ11: 44244 | AR11: 44274 | AT11: =AV11/1.05 -> 588571.43 | AU11: =AV11-AT11 -> 29428.571 | AV11: 618000 | AX11: 30000 | AY11: =AX11/AV11 -> 0.048543689 | AZ11: Bhawanjot & Sharandeep Grewal | BA11: =IFERROR(AV11/P11,0) -> 1.0564103 | BB11: 44208
B12: 317 Aspenmere Way, Chestermere | C12: 1513280 | D12: 44 | E12: 20 | F12: Chestermere | G12: Cost | H12: Pre-Sold | I12: Construction | J12: 0.55 | K12: 0.75 | L12: 0.65 | M12: 205000 | N12: 200000 | O12: 200000 | P12: 780000 | Q12: 780000 | R12: 237.37066 | S12: 5511.1168 | T12: 3286 | U12: 407500 | V12: 124.01096 | W12: 110000 | X12: 349375 | Y12: 459375 | Z12: 0.58894231 | AA12: 0.75 | AB12: 434925 | AC12: 44008 | AD12: 110000 | AE12: 290695 | AF12: 400695 | AG12: 0 | AH12: 34230 | AI12: 0.94 | AJ12: 0 | AK12: 24450 | AL12: 58680 | AM12: 400695 | AO12: 400695 | AP12: 44067 | AQ12: 44068 | AT12: 743333.33 | AU12: 37166.667 | AV12: 780500 | AX12: 55000 | AY12: 0.070467649 | AZ12: Jasprett Singh Sandhu & Rajwinder Kaur Sandhu | BA12: 1.000641 | BB12: 43791
B13: 488 Muirfield Crescent, Lyalta | C13: 0811158 | D13: 4 | E13: N/A | F13: Rural Alberta | G13: Cost | H13: Speculative | I13: Completed | J13: 0.5 | K13: 0.675 | L13: 0.575 | M13: 134400 | N13: 70000 | O13: 70000 | P13: 463000 | Q13: 463000 | R13: 314.11126 | S13: 7803.8275 | T13: 1474 | U13: 271200 | V13: 183.98915 | W13: 35000 | X13: 231225 | Y13: 266225 | Z13: 0.575 | AA13: 0.65637327 | AB13: 266225 | AC13: 44008 | AD13: 35000 | AE13: 230851.25 | AF13: 265851.25 | AG13: 0 | AH13: 373.75 | AI13: 1 | AJ13: 0 | AK13: 0 | AL13: 373.75 | AM13: 265851.25 | AO13: 265851.25 | AP13: 44236 | AQ13: 44257 | AR13: 44295 | AT13: 449523.81 | AU13: 22476.19 | AV13: 472000 | AX13: 15000 | AY13: 0.031779661 | AZ13: Sean Hynes and Joanne Byrne | BA13: 1.0194384 | BB13: 44147
B14: 725 Marina Drive | C14: 1910205 | D14: 2 | E14: 1 | F14: Chestermere | G14: Cost | H14: Pre-Sold | I14: Construction | J14: 0.6 | K14: 0.775 | L14: 0.675 | M14: 205234 | N14: 180000 | O14: 180000 | P14: 684000 | Q14: 683500 | R14: 223.5121 | S14: 4898 | T14: 3058 | U14: 383900 | V14: 125.53957 | W14: 108000 | X14: 348578.85 | Y14: 456578.85 | Z14: 0.66800124 | AA14: 0.775 | AB14: 412430.35 | AC14: 44154 | AD14: 108000 | AE14: 304430.35 | AF14: 412430.35 | AG14: 0 | AH14: 0 | AI14: 0.885 | AJ14: 0 | AK14: 44148.5 | AL14: 44148.5 | AM14: 412430.35 | AO14: 412430.35 | AP14: 44300 | AQ14: 44305 | AR14: 44335 | AT14: 650952.38 | AU14: 32547.619 | AV14: 683500 | AX14: 34175 | AY14: 0.05 | AZ14: Kulbir Singh, Pawanpreet Singh & Bhanwarpreet Singh | BA14: 0.99926901 | BB14: 43990
B15: 1512 25 Avenue SW, Calgary | C15: 2011851 | D15: 3 | E15: N/A | F15: Calgary | G15: Cost | H15: Speculative | I15: Construction | J15: 0.5 | K15: 0.725 | L15: 0.625 | M15: 153750 | N15: 160000 | O15: 153750 | P15: 539900 | Q15: 538000 | R15: 381.83109 | S15: 1400 | T15: 1409 | U15: 280901.07 | V15: 199.36201 | W15: 76875 | X15: 238247.03 | Y15: 315122.03 | Z15: 0.58572867 | AA15: 0.725 | AB15: 285908.32 | AC15: 44008 | AD15: 76875 | AE15: 209033.32 | AF15: 285908.32 | AG15: 0 | AH15: 0 | AI15: 0.896 | AJ15: 0 | AK15: 29213.711 | AL15: 29213.707 | AM15: 285908.32 | AO15: 285908.32 | AP15: 44305 | AQ15: 44306 | AR15: 44335 | AT15: 512380.95 | AU15: 25619.048 | AV15: 538000 | AX15: 10000 | AY15: 0.018587361 | AZ15: Tanya Morahan | BA15: 0.99648083 | BB15: 44257
B16: 130 Kinniburgh Crescent | C16: 1812008 | D16: 11 | E16: 42 | F16: Chestermere | G16: Cost | H16: Pre-Sold | I16: Construction | J16: 0.6 | K16: 0.775 | L16: 0.675 | M16: 187000 | N16: 215000 | O16: 187000 | P16: 685000 | Q16: 685000 | R16: 230.71741 | S16: 5748 | T16: 2969 | U16: 388300 | V16: 130.78478 | W16: 112200 | X16: 333657.5 | Y16: 445857.5 | Z16: 0.65088686 | AA16: 0.775 | AB16: 427995.7 | AC16: 44154 | AD16: 93500 | AE16: 334495.7 | AF16: 427995.7 | AG16: 0 | AH16: 0 | AI16: 0.954 | AJ16: 0 | AK16: 17861.8 | AL16: 17861.8 | AM16: 427995.7 | AO16: 427995.7 | AP16: 44330 | AQ16: 44341 | AR16: 44375 | AT16: 669828.57 | AU16: 33491.429 | AV16: 703320 | AX16: 10000 | AY16: 0.014218279 | AZ16: Rajwinder Bajwa & Rajkamal Bajwa | BA16: 1.0267445 | BB16: 44195
B17: 1510 25 Avenue SW, Calgary | C17: 2011851 | D17: 4 | E17: N/A | F17: Calgary | G17: Cost | H17: Speculative | I17: Completed | J17: 0.5 | K17: 0.725 | L17: 0.625 | M17: 153750 | N17: 160000 | O17: 153750 | P17: 539900 | Q17: 537000 | R17: 381.12136 | S17: 1400 | T17: 1409 | U17: 280901.07 | V17: 199.36201 | W17: 76875 | X17: 238247.03 | Y17: 315122.03 | Z17: 0.58681942 | AA17: 0.725 | AB17: 309223.1 | AC17: 44008 | AD17: 76875 | AE17: 238247.03 | AF17: 315122.03 | AG17: 0 | AH17: -5898.93 | AI17: 0.979 | AJ17: 0 | AK17: 5898.9225 | AL17: -0.0032687991 | AM17: 315122.03 | AO17: 315122.03 | AP17: 44390 | AQ17: 44398 | AR17: 44420 | AT17: 511428.57 | AU17: 25571.429 | AV17: 537000 | AX17: 10000 | AY17: 0.018621974 | AZ17: Rejish Thomas & Ratika Srivastava | BA17: 0.99462863 | BB17: 44278
B18: 1514 25 Avenue SW, Calgary | C18: 2011851 | D18: 2 | E18: N/A | F18: Calgary | G18: Cost | H18: Speculative | I18: Completed | J18: 0.5 | K18: 0.725 | L18: 0.625 | M18: 153750 | N18: 160000 | O18: 153750 | P18: 539900 | Q18: 532000 | R18: 377.57275 | S18: 1400 | T18: 1409 | U18: 280901.07 | V18: 199.36201 | W18: 76875 | X18: 238247.03 | Y18: 315122.03 | Z18: 0.59233464 | AA18: 0.725 | AB18: 309223.1 | AC18: 44008 | AD18: 76875 | AE18: 238247.03 | AF18: 315122.03 | AG18: 0 | AH18: -5898.93 | AI18: 0.979 | AJ18: 0 | AK18: 5898.9225 | AL18: -0.0032687991 | AM18: 315122.03 | AO18: 315122.03 | AQ18: 44393 | AR18: 44420 | AT18: 506666.67 | AU18: 25333.333 | AV18: 532000 | AX18: 10000 | AY18: 0.018796992 | AZ18: Carson Kotnyek | BA18: 0.98536766 | BB18: 44344
B19: 1516 25 Avenue SW, Calgary | C19: 2011851 | D19: 1 | E19: N/A | F19: Calgary | G19: Cost | H19: Speculative | I19: Completed | J19: 0.5 | K19: 0.725 | L19: 0.625 | M19: 153750 | N19: 160000 | O19: 153750 | P19: 539900 | Q19: 539900 | R19: 383.17956 | S19: 1400 | T19: 1409 | U19: 280901.07 | V19: 199.36201 | W19: 76875 | X19: 238247.03 | Y19: 315122.03 | Z19: 0.5836674 | AA19: 0.725 | AB19: 309223.1 | AC19: 44008 | AD19: 76875 | AE19: 238247.03 | AF19: 315122.03 | AG19: 0 | AH19: -5898.93 | AI19: 0.979 | AJ19: 0 | AK19: 5898.9225 | AL19: -0.0032687988 | AM19: 315122.03 | AO19: 315122.03 | AP19: 44392 | AQ19: 44398 | AR19: 44420 | AT19: 519047.62 | AU19: 25952.381 | AV19: 545000 | AX19: 50000 | AY19: 0.091743119 | AZ19: Rajiv Srivastava | BA19: 1.0094462 | BB19: 44305
B20: 40 Waterford Heights | C20: 2110528 | D20: 2 | E20: 5 | F20: Chestermere | G20: Cost | H20: Speculative | I20: Completed | J20: 0.5 | K20: 0.725 | L20: 0.625 | M20: 232800 | N20: 240000 | O20: 232800 | P20: 705000 | Q20: 705000 | R20: 306.25543 | S20: 4984 | T20: 2302 | U20: 366900 | V20: 159.38315 | W20: 116400 | X20: 318382.5 | Y20: 434782.5 | Z20: 0.61671277 | AA20: 0.725 | AB20: 428545.2 | AC20: 44314 | AD20: 116400 | AE20: 318382.5 | AF20: 434782.5 | AG20: 0 | AH20: -6237.3 | AI20: 0.983 | AJ20: 0 | AK20: 6237.3 | AL20: 0 | AM20: 434782.5 | AO20: 434782.5 | AP20: 44418 | AQ20: 44424 | AR20: 44456 | AT20: 723809.52 | AU20: 36190.476 | AV20: 760000 | AZ20: Patrick Hanly & Aliya Hanly | BA20: 1.0780142 | BB20: 44293
B21: 225 Marina Key | C21: 1910205 | D21: 2 | E21: 24 | F21: Chestermere | G21: Cost | H21: Pre-Sold | I21: Construction | J21: 0.6 | K21: 0.775 | L21: 0.675 | M21: 190000 | N21: 135000 | O21: 135000 | P21: 465000 | Q21: 465000 | R21: 226.05737 | S21: 4542.3658 | T21: 2057 | U21: 236200 | V21: 114.82742 | W21: 81000 | X21: 232875 | Y21: 313875 | Z21: 0.675 | AA21: 0.73645002 | AB21: 311985.4 | AC21: 44281 | AD21: 67500 | AE21: 246375 | AF21: 313875 | AG21: 0 | AH21: -1889.6 | AI21: 0.992 | AJ21: 0 | AK21: 1889.6 | AL21: 0 | AM21: 313875 | AO21: 313875 | AP21: 44431 | AQ21: 44438 | AR21: 44462 | AT21: 466666.67 | AU21: 23333.333 | AV21: 490000 | AX21: 10000 | AY21: 0.020408163 | AZ21: Patrick McGrath | BA21: 1.0537634 | BB21: 44285 | BC21: Pre-sale purchaser mortgage financing approval letter from TD has been obtained
B22: 229 Marina Key | C22: 1910205 | D22: 2 | E22: 25 | F22: Chestermere | G22: Cost | H22: Pre-Sold | I22: Construction | J22: 0.6 | K22: 0.775 | L22: 0.675 | M22: 190000 | N22: 140000 | O22: 140000 | P22: 485000 | Q22: 479900.4 | R22: 221.56066 | S22: 6286.1176 | T22: 2166 | U22: 242500 | V22: 111.95753 | W22: 84000 | X22: 239932.77 | Y22: 323932.77 | Z22: 0.675 | AA22: 0.7489775 | AB22: 321750.27 | AC22: 44281 | AD22: 84000 | AE22: 239932.77 | AF22: 323932.77 | AG22: 0 | AH22: -2182.5 | AI22: 0.991 | AJ22: 0 | AK22: 2182.5 | AL22: 0 | AM22: 323932.77 | AO22: 323932.77 | AP22: 44431 | AQ22: 44435 | AR22: 44462 | AT22: 457048 | AU22: 22852.4 | AV22: 479900.4 | AX22: 25750 | AY22: 0.053656967 | AZ22: Steven Anthony Douglas | BA22: 0.98948536 | BB22: 44048
B23: 733 Marina Drive | C23: 1910205 | D23: 2 | E23: 3 | F23: Chestermere | G23: Cost | H23: Pre-Sold | I23: Construction | J23: 0.6 | K23: 0.775 | L23: 0.675 | M23: 205234 | N23: 192000 | O23: 192000 | P23: 577000 | Q23: 577000 | R23: 288.9334 | S23: 4898 | T23: 1997 | U23: 282100 | V23: 141.26189 | W23: 115200 | X23: 262483.85 | Y23: 377683.85 | Z23: 0.65456473 | AA23: 0.775 | AB23: 376273.35 | AC23: 44281 | AD23: 115200 | AE23: 262483.85 | AF23: 377683.85 | AG23: 0 | AH23: -1410.5 | AI23: 0.995 | AJ23: 0 | AK23: 1410.5 | AL23: 0 | AM23: 377683.85 | AO23: 377683.85 | AP23: 44447 | AQ23: 44452 | AR23: 44477 | AT23: 549523.8 | AU23: 27476.2 | AV23: 577000 | AX23: 40000 | AY23: 0.06932409 | AZ23: Alexandra Gingras & Brad Kraus | BA23: 1 | BB23: 44164
B24: 44 Waterford Heights | C24: 2110528 | D24: 2 | E24: 4 | F24: Chestermere | G24: Cost | H24: Pre-Sold | I24: Construction | J24: 0.6 | K24: 0.775 | L24: 0.675 | M24: 232800 | N24: 240000 | O24: 232800 | P24: 890000 | Q24: 890000 | R24: 286.35779 | S24: 5414 | T24: 3108 | U24: 521400 | V24: 167.76062 | W24: 139680 | X24: 400320 | Y24: 540000 | Z24: 0.60674157 | AA24: 0.71599045 | AB24: 515494.2 | AC24: 44314 | AD24: 139680 | AE24: 375814.2 | AF24: 515494.2 | AG24: 0 | AH24: 0 | AI24: 0.953 | AJ24: 0 | AK24: 24505.8 | AL24: 24505.8 | AM24: 515494.2 | AO24: 515494.2 | AP24: 44469 | AQ24: 44473 | AR24: 44491 | AT24: 850476.19 | AU24: 42523.81 | AV24: 893000 | AX24: 177000 | AY24: 0.19820829 | AZ24: Gulvinder Singh Khosa | BA24: 1.0033708 | BB24: 44063
B25: 74 Waterford Road | C25: 2110528 | D25: 6 | E25: 19 | F25: Chestermere | G25: Cost | H25: Pre-Sold | I25: Construction | J25: 0.6 | K25: 0.775 | L25: 0.675 | M25: 191250 | N25: 185000 | O25: 185000 | P25: 550000 | Q25: 550000 | R25: 258.70179 | S25: 5185 | T25: 2126 | U25: 355400 | V25: 167.16839 | W25: 111000 | X25: 260250 | Y25: 371250 | Z25: 0.675 | AA25: 0.67913656 | AB25: 329668.2 | AC25: 44314 | AD25: 111000 | AE25: 218668.2 | AF25: 329668.2 | AG25: 0 | AH25: 0 | AI25: 0.883 | AJ25: 0 | AK25: 41581.8 | AL25: 41581.8 | AM25: 329668.2 | AO25: 329668.2 | AP25: 44477 | AQ25: 44484 | AR25: 44519 | AT25: 571955.44 | AU25: 28597.772 | AV25: 600553.21 | AX25: 33500 | AY25: 0.055781901 | AZ25: Deepak Lodhia & Chandni Nitin Rama | BA25: 1.0919149 | BB25: 44023 | BC25: Pre-sale purchaser mortgage financing approval letter has been obtained
B26: 61 Waterford Road | C26: 2110528 | D26: 2 | E26: 18 | F26: Chestermere | G26: Cost | H26: Pre-Sold | I26: Construction | J26: 0.6 | K26: 0.775 | L26: 0.675 | M26: 218250 | N26: 200000 | O26: 200000 | P26: 820000 | Q26: 820000 | R26: 304.49313 | S26: 4886.8106 | T26: 2693 | U26: 467400 | V26: 173.56108 | W26: 120000 | X26: 411378.75 | Y26: 531378.75 | Z26: 0.64802287 | AA26: 0.775 | AB26: 489312.75 | AC26: 44421 | AD26: 120000 | AE26: 369312.75 | AF26: 489312.75 | AG26: 0 | AH26: 0 | AI26: 0.91 | AJ26: 0 | AK26: 42066 | AL26: 42066 | AM26: 489312.75 | AO26: 489312.75 | AP26: 44511 | AQ26: 44523 | AR26: 44553 | AT26: 780952.38 | AU26: 39047.619 | AV26: 820000 | AX26: 82000 | AY26: 0.1 | AZ26: Mavindeep Gill & Sandeep Gill | BA26: 1 | BB26: 44209
B27: 724 Marina Drive | C27: 1910205 | D27: 1 | E27: 1 | F27: Chestermere | G27: Cost | H27: Pre-Sold | I27: Construction | J27: 0.6 | K27: 0.775 | L27: 0.675 | M27: 204077 | N27: 200000 | O27: 200000 | P27: 715000 | Q27: 713102.25 | R27: 271.658 | S27: 5259 | T27: 2625 | U27: 380400 | V27: 144.91429 | W27: 120000 | X27: 332969.67 | Y27: 452969.67 | Z27: 0.63520999 | AA27: 0.775 | AB27: 389062.48 | AC27: 44314 | AD27: 120000 | AE27: 269062.48 | AF27: 389062.48 | AG27: 0 | AH27: 0 | AI27: 0.832 | AJ27: 0 | AK27: 63907.2 | AL27: 63907.195 | AM27: 389062.48 | AO27: 389062.48 | AP27: 44529 | AQ27: 44547 | AR27: 44210 | AT27: 679145 | AU27: 33957.25 | AV27: 713102.25 | AX27: 67000 | AY27: 0.09395567 | AZ27: Sylvester Francis & Manveen Reen | BA27: 0.9973458 | BB27: 44140
B28: 7 North Bridges Road, Langdon | C28: 2011558 | D28: 2 | E28: 2 | F28: Langdon | G28: Cost | H28: Speculative | I28: Completed | J28: 0.5 | K28: 0.7 | L28: 0.6 | M28: 170000 | N28: 165000 | O28: 165000 | P28: 675000 | Q28: 675000 | R28: 373.13433 | S28: 8385 | T28: 1809 | U28: 433100 | V28: 239.41404 | W28: 82500 | X28: 277500 | Y28: 360000 | Z28: 0.53333333 | AA28: 0.59691593 | AB28: 337045.7 | AC28: 44154 | AD28: 82500 | AE28: 239545.7 | AF28: 322045.7 | AG28: 0 | AH28: 15000 | AI28: 0.947 | AJ28: 0 | AK28: 22954.3 | AL28: 37954.3 | AM28: 322045.7 | AO28: 0 | AP28: 44545 | AQ28: 44550 | AR28: 44210 | AT28: 785677.38 | AU28: 39283.869 | AV28: 824961.25 | AX28: 82496.25 | AY28: 0.10000015 | AZ28: Kathy & John Klassen | BA28: 1.2221648 | BB28: 44524
B29: 77 Waterford Road | C29: 2110528 | D29: 2 | E29: 22 | F29: Chestermere | G29: Cost | H29: Pre-Sold | I29: Construction | J29: 0.6 | K29: 0.775 | L29: 0.675 | M29: 223100 | N29: 200000 | O29: 200000 | P29: 765000 | Q29: 765000 | R29: 274.78448 | S29: 4980.026 | T29: 2784 | U29: 442900 | V29: 159.08764 | W29: 120000 | X29: 396150 | Y29: 516150 | Z29: 0.67470588 | AA29: 0.775 | AB29: 494005 | AC29: 44421 | AD29: 120000 | AE29: 396150 | AF29: 516150 | AG29: 0 | AH29: -22145 | AI29: 0.95 | AJ29: 0 | AK29: 22145 | AL29: 0 | AM29: 516150 | AO29: 516150 | AP29: 44587 | AQ29: 44606 | AR29: 44631 | AT29: 728571.43 | AU29: 36428.571 | AV29: 765000 | AX29: 88000 | AY29: 0.11503268 | AZ29: Ami Chandra & Manjula Chandra | BA29: 1 | BB29: 43869
B30: 129 North Bridges Bay, Langdon | C30: 2011558 | D30: 1 | E30: 43 | F30: Langdon | G30: Cost | H30: Pre-Sold | I30: Construction | J30: 0.5 | K30: 0.75 | L30: 0.65 | M30: 184000 | N30: 185000 | O30: 184000 | P30: 660000 | Q30: 657000 | R30: 310.78524 | S30: 8955 | T30: 2114 | U30: 405900 | V30: 192.00568 | W30: 92000 | X30: 335050 | Y30: 427050 | Z30: 0.65 | AA30: 0.72393626 | AB30: 220852.8 | AC30: 44470 | AD30: 92000 | AE30: 128852.8 | AF30: 220852.8 | AG30: 0 | AH30: 0 | AI30: 0.492 | AJ30: 0 | AK30: 206197.2 | AL30: 206197.2 | AM30: 220852.8 | AO30: 220852.8 | AP30: 44602 | AQ30: 44614 | AR30: 44638 | AT30: 625714.29 | AU30: 31285.714 | AV30: 657000 | AW30: 6938.62 | AX30: 37500 | AY30: 0.057077626 | AZ30: Sanjeev & Krishna Chavda | BA30: 0.99545455 | BB30: 44229 | BC30: Pre-sale purchaser mortgage financing approval letter has been obtained
B31: 85 Waterford Road | C31: 2110528 | D31: 2 | E31: 24 | F31: Chestermere | G31: Cost | H31: Pre-Sold | I31: Construction | J31: 0.6 | K31: 0.775 | L31: 0.675 | M31: 223100 | N31: 200000 | O31: 200000 | P31: 770000 | Q31: 765000 | R31: 271.85501 | S31: 4980.026 | T31: 2814 | U31: 449900 | V31: 159.87918 | W31: 120000 | X31: 396375 | Y31: 516375 | Z31: 0.675 | AA31: 0.7672734 | AB31: 426395 | AC31: 44421 | AD31: 120000 | AE31: 306395 | AF31: 426395 | AG31: 0 | AH31: 0 | AI31: 0.8 | AJ31: 0 | AK31: 89980 | AL31: 89980 | AM31: 426395 | AO31: 426395 | AP31: 44599 | AQ31: 44614 | AR31: 44638 | AT31: 728571.43 | AU31: 36428.571 | AV31: 765000 | AX31: 88000 | AY31: 0.11503268 | AZ31: Kamal Bulsara & Jotika Bulsara | BA31: 0.99350649 | BB31: 43869
B32: 12 Waterford Heights | C32: 2110528 | D32: 2 | E32: 12 | F32: Chestermere | G32: Cost | H32: Pre-Sold | I32: Construction | J32: 0.6 | K32: 0.775 | L32: 0.675 | M32: 218250 | N32: 250000 | O32: 218250 | P32: 780000 | Q32: 780000 | R32: 294.89603 | S32: 4919.1023 | T32: 2645 | U32: 429400 | V32: 162.34405 | W32: 130950 | X32: 370978.75 | Y32: 501928.75 | Z32: 0.6434984 | AA32: 0.775 | AB32: 368814.75 | AC32: 44421 | AD32: 130950 | AE32: 237864.75 | AF32: 368814.75 | AG32: 0 | AH32: 0 | AI32: 0.69 | AJ32: 0 | AK32: 133114 | AL32: 133114 | AM32: 368814.75 | AO32: 368814.75 | AP32: 44606 | AQ32: 44620 | AR32: 44650 | AT32: 742857.14 | AU32: 37142.857 | AV32: 780000 | AX32: 54390 | AY32: 0.069730769 | AZ32: Angrej Malhi | BA32: 1 | BB32: 44093
B33: 737 Marina Drive | C33: 1910205 | D33: 2 | E33: 4 | F33: Chestermere | G33: Cost | H33: Pre-Sold | I33: Construction | J33: 0.6 | K33: 0.775 | L33: 0.675 | M33: 205234 | N33: 175000 | O33: 175000 | P33: 750000 | Q33: 745465.25 | R33: 260.74335 | S33: 4899 | T33: 2859 | U33: 458100 | V33: 160.23085 | W33: 105000 | X33: 398189.04 | Y33: 503189.04 | Z33: 0.675 | AA33: 0.75857569 | AB33: 418440.54 | AC33: 44491 | AD33: 152117.28 | AE33: 266323.26 | AF33: 418440.54 | AG33: 0 | AH33: 0 | AI33: 0.815 | AJ33: 0 | AK33: 84748.5 | AL33: 84748.504 | AM33: 418440.54 | AO33: 418440.54 | AP33: 44627 | AQ33: 44636 | AR33: 44663 | AT33: 709966.9 | AU33: 35498.345 | AV33: 745465.25 | AW33: 23530.5 | AX33: 74550 | AY33: 0.10000466 | AZ33: Puneet & Yashwinder Matharoo | BA33: 0.99395367 | BB33: 44158
B34: 73 Waterford Road | C34: 2110528 | D34: 2 | E34: 21 | F34: Chestermere | G34: Cost | H34: Pre-Sold | I34: Construction | J34: 0.6 | K34: 0.775 | L34: 0.675 | M34: 220708 | N34: 200000 | O34: 200000 | P34: 765000 | Q34: 761783.4 | R34: 354.64777 | S34: 4972.9218 | T34: 2148 | U34: 445400 | V34: 207.35568 | W34: 120000 | X34: 394203.8 | Y34: 514203.8 | Z34: 0.675 | AA34: 0.77195259 | AB34: 337380 | AC34: 44421 | AD34: 120000 | AE34: 217380 | AF34: 337380 | AG34: 337380 | AH34: 0 | AI34: 0.603 | AJ34: 538755.39 | AK34: 176823.8 | AL34: 176823.8 | AM34: 337380 | AO34: 337380 | AP34: 44665 | AQ34: 44669 | AR34: 44697 | AT34: 725508 | AU34: 36275.4 | AV34: 761783.4 | AX34: 75000 | AY34: 0.098453182 | AZ34: Adam Virgo | BA34: 0.99579529 | BB34: 44111
B35: 8 Waterford Heights | C35: 2110528 | D35: 2 | E35: 13 | F35: Chestermere | G35: Cost | H35: Pre-Sold | I35: Construction | J35: 0.6 | K35: 0.775 | L35: 0.675 | M35: 207000 | N35: 250000 | O35: 207000 | P35: 735000 | Q35: 730364.25 | R35: 298.10786 | S35: 4888 | T35: 2450 | U35: 422200 | V35: 172.32653 | W35: 124200 | X35: 363430 | Y35: 487630 | Z35: 0.66765316 | AA35: 0.775 | AB35: 398968 | AC35: 44491 | AD35: 124200 | AE35: 274768 | AF35: 398968 | AG35: 0 | AH35: 0 | AI35: 0.79 | AJ35: 0 | AK35: 88662 | AL35: 88662 | AM35: 398968 | AO35: 398968 | AP35: 44677 | AQ35: 44683 | AR35: 44714 | AT35: 695585 | AU35: 34779.25 | AV35: 730364.25 | AW35: 4168.5 | AX35: 50000 | AY35: 0.068458992 | AZ35: Satbir Sidhu & Manjot Toor | BA35: 0.99369286 | BB35: 44214 | BC35: Pre-sale purchaser mortgage financing approval letter has been obtained
B36: 97 North Bridges Bay, Langdon | C36: 2011558 | D36: 1 | E36: 35 | F36: Langdon | G36: Cost | H36: Pre-Sold | I36: Construction | J36: 0.5 | K36: 0.75 | L36: 0.65 | M36: 184000 | N36: 185000 | O36: 184000 | P36: 695000 | Q36: 694773.45 | R36: 384.70291 | S36: 8860 | T36: 1806 | U36: 418900 | V36: 231.94906 | W36: 92000 | X36: 359602.74 | Y36: 451602.74 | Z36: 0.65 | AA36: 0.74905083 | AB36: 310852.34 | AC36: 44470 | AD36: 92000 | AE36: 218852.34 | AF36: 310852.34 | AG36: 0 | AH36: 0 | AI36: 0.664 | AJ36: 0 | AK36: 140750.4 | AL36: 140750.4 | AM36: 310852.34 | AO36: 310852.34 | AP36: 44671 | AQ36: 44686 | AR36: 44714 | AT36: 661689 | AU36: 33084.45 | AV36: 694773.45 | AW36: 3313 | AX36: 45000 | AY36: 0.064769314 | AZ36: Morgan & Christopher Shervey | BA36: 0.99967403 | BB36: 44283 | BC36: Grandfathered - Mortgage financing approval letter has also been received
B37: 113 North Bridges Bay, Langdon | C37: 2011558 | D37: 1 | E37: 39 | F37: Langdon | G37: Cost | H37: Pre-Sold | I37: Construction | J37: 0.5 | K37: 0.75 | L37: 0.65 | M37: 184000 | N37: 185000 | O37: 184000 | P37: 685000 | Q37: 682500 | R37: 259.21003 | S37: 8860 | T37: 2633 | U37: 437400 | V37: 166.12229 | W37: 92000 | X37: 351625 | Y37: 443625 | Z37: 0.65 | AA37: 0.71391213 | AB37: 334275 | AC37: 44470 | AD37: 92000 | AE37: 242275 | AF37: 334275 | AG37: 0 | AH37: 0 | AI37: 0.75 | AJ37: 0 | AK37: 109350 | AL37: 109350 | AM37: 334275 | AO37: 334275 | AP37: 44711 | AQ37: 44718 | AR37: 44748 | AT37: 650000 | AU37: 32500 | AV37: 682500 | AW37: 16625.35 | AX37: 35000 | AY37: 0.051282051 | AZ37: Dean Davies & Kimberley Davies | BA37: 0.99635036 | BB37: 44205 | BC37: Grandfathered - Mortgage financing approval letter has also been received
B38: 4 Waterford Heights | C38: 2110528 | D38: 2 | E38: 14 | F38: Chestermere | G38: Cost | H38: Pre-Sold | I38: Construction | J38: 0.6 | K38: 0.775 | L38: 0.675 | M38: 208800 | N38: 200000 | O38: 200000 | P38: 660000 | Q38: 650000 | R38: 258.65499 | S38: 5663 | T38: 2513 | U38: 363200 | V38: 144.52845 | W38: 120000 | X38: 318750 | Y38: 438750 | Z38: 0.675 | AA38: 0.76704545 | AB38: 362478 | AC38: 44582 | AD38: 120000 | AE38: 242478 | AF38: 362478 | AG38: 0 | AH38: 0 | AI38: 0.79 | AJ38: 0 | AK38: 76272 | AL38: 76272 | AM38: 362478 | AO38: 362478 | AP38: 44727 | AQ38: 44728 | AR38: 44761 | AT38: 619047.62 | AU38: 30952.381 | AV38: 650000 | AW38: 25972.64 | AX38: 32000 | AY38: 0.049230769 | AZ38: Kewal Saggu & Balbir Matharu | BA38: 0.98484848 | BB38: 44180 | BC38: Pre-sale purchaser mortgage financing pre-approval letter has been obtained
B39: 93 North Bridges Bay, Langdon | C39: 2011558 | D39: 1 | E39: 34 | F39: Langdon | G39: Cost | H39: Pre-Sold | I39: Construction | J39: 0.5 | K39: 0.75 | L39: 0.65 | M39: 184000 | N39: 185000 | O39: 184000 | P39: 760000 | Q39: 756750.75 | R39: 304.40497 | S39: 10193 | T39: 2486 | U39: 489900 | V39: 197.06356 | W39: 92000 | X39: 399887.99 | Y39: 491887.99 | Z39: 0.65 | AA39: 0.72991243 | AB39: 464453.59 | AC39: 44470 | AD39: 92000 | AE39: 372453.59 | AF39: 464453.59 | AG39: 0 | AH39: 0 | AI39: 0.944 | AJ39: 0 | AK39: 27434.4 | AL39: 27434.398 | AM39: 464453.59 | AO39: 464453.59 | AQ39: 44757 | AR39: 44781 | AT39: 720715 | AU39: 36035.75 | AV39: 756750.75 | AW39: 10672.75 | AX39: 75000 | AY39: 0.09910793 | AZ39: Mark & Carla Schwartz | BA39: 0.99572467 | BB39: 44277
B40: 78 Waterford Road | C40: 2110528 | D40: 6 | E40: 20 | F40: Chestermere | G40: Cost | H40: Pre-Sold | I40: Construction | J40: 0.6 | K40: 0.775 | L40: 0.675 | M40: 191250 | N40: 175000 | O40: 175000 | P40: 690000 | Q40: 686344.95 | R40: 226.74098 | S40: 5185 | T40: 3027 | U40: 463400 | V40: 153.08887 | W40: 105000 | X40: 358282.84 | Y40: 463282.84 | Z40: 0.675 | AA40: 0.7076802 | AB40: 407674.84 | AC40: 44582 | AD40: 105000 | AE40: 302674.84 | AF40: 407674.84 | AG40: 0 | AH40: 0 | AI40: 0.88 | AJ40: 0 | AK40: 55608 | AL40: 55608.001 | AM40: 407674.84 | AO40: 407674.84 | AP40: 44762 | AQ40: 44775 | AR40: 44802 | AT40: 653661.86 | AU40: 32683.093 | AV40: 686344.95 | AX40: 40000 | AY40: 0.058279732 | AZ40: Victor & Sheryl Vicente | BA40: 0.99470283 | BB40: 44178
B41: 101 North Bridges Bay, Langdon | C41: 2011558 | D41: 1 | E41: 36 | F41: Langdon | G41: Cost | H41: Pre-Sold | I41: Construction | J41: 0.5 | K41: 0.75 | L41: 0.65 | M41: 184000 | N41: 185000 | O41: 184000 | P41: 860000 | Q41: 855492.75 | R41: 473.69477 | S41: 8860 | T41: 1806 | U41: 542400 | V41: 300.33223 | W41: 92000 | X41: 428000 | Y41: 520000 | Z41: 0.60783683 | AA41: 0.71585903 | AB41: 384400 | AC41: 44470 | AD41: 92000 | AE41: 292400 | AF41: 384400 | AG41: 0 | AH41: 0 | AI41: 0.75 | AJ41: 0 | AK41: 135600 | AL41: 135600 | AM41: 384400 | AO41: 384400 | AQ41: 44776 | AR41: 44802 | AT41: 814755 | AU41: 40737.75 | AV41: 855492.75 | AW41: -5743.5 | AX41: 85500 | AY41: 0.099942402 | AZ41: Carole Campbell | BA41: 0.99475901 | BB41: 44287
B42: 81 Waterford Road | C42: 2110528 | D42: 2 | E42: 23 | F42: Chestermere | G42: Cost | H42: Pre-Sold | I42: Construction | J42: 0.6 | K42: 0.775 | L42: 0.675 | M42: 239900 | N42: 300000 | O42: 239900 | P42: 960000 | Q42: 801979.5 | R42: 310.60399 | S42: 5413.3806 | T42: 2582 | U42: 457400 | V42: 177.1495 | W42: 143940 | X42: 396060 | Y42: 540000 | Z42: 0.67333392 | AA42: 0.7744156 | AB42: 425650 | AC42: 44645 | AD42: 143940 | AE42: 281710 | AF42: 425650 | AG42: 0 | AH42: 0 | AI42: 0.75 | AJ42: 0 | AK42: 114350 | AL42: 114350 | AM42: 425650 | AO42: 425650 | AQ42: 44799 | AR42: 44827 | AT42: 763790 | AU42: 38189.5 | AV42: 801979.5 | AX42: 40000 | AY42: 0.049876587 | AZ42: Michelle Pickard & Brent Pickard | BA42: 0.83539531 | BB42: 44305 | BC42: Pre-sale purchaser mortgage financing pre-approval letter has been obtained
B43: 28 Waterford Heights | C43: 2110528 | D43: 2 | E43: 8 | F43: Chestermere | G43: Cost | H43: Pre-Sold | I43: Construction | J43: 0.6 | K43: 0.775 | L43: 0.675 | M43: 220708 | N43: 250000 | O43: 220708 | P43: 920000 | Q43: 910000 | R43: 313.68494 | S43: 4980 | T43: 2901 | U43: 531100 | V43: 183.0748 | W43: 132424.8 | X43: 407575.2 | Y43: 540000 | Z43: 0.59340659 | AA43: 0.71826849 | AB43: 449713 | AC43: 44491 | AD43: 132424.8 | AE43: 317288.2 | AF43: 449713 | AG43: 0 | AH43: 0 | AI43: 0.83 | AJ43: 0 | AK43: 90287 | AL43: 90287 | AM43: 449713 | AO43: 449713 | AQ43: 44802 | AR43: 44827 | AT43: 866666.67 | AU43: 43333.333 | AV43: 910000 | AX43: 86000 | AY43: 0.094505495 | AZ43: Sukhjinder Singh | BA43: 0.98913043 | BB43: 44233
B44: 89 North Bridges Bay, Langdon | C44: 2011558 | D44: 1 | E44: 33 | F44: Langdon | G44: Cost | H44: Pre-Sold | I44: Construction | J44: 0.5 | K44: 0.75 | L44: 0.65 | M44: 184000 | N44: 185000 | O44: 184000 | P44: 750000 | Q44: 750000 | R44: 255.18884 | S44: 8860 | T44: 2939 | U44: 590900 | V44: 201.05478 | W44: 92000 | X44: 395500 | Y44: 487500 | Z44: 0.65 | AA44: 0.62911343 | AB44: 212731.5 | AC44: 44470 | AD44: 92000 | AE44: 120731.5 | AF44: 212731.5 | AG44: 0 | AH44: 0 | AI44: 0.535 | AJ44: 0 | AK44: 274768.5 | AL44: 274768.5 | AM44: 212731.5 | AO44: 212731.5 | AQ44: 44803 | AR44: 44827 | AT44: 885637.85 | AU44: 44281.892 | AV44: 929919.74 | AX44: 94812 | AY44: 0.10195719 | AZ44: Robert & Jennifer Milne | BA44: 1.239893 | BB44: 44448 | BC44: Grandfathered - Deposit of $55K has been received to date. Remaining deposit of $40K to be received February 28, 2022. Total deposit per PSA is $92,991.90.
B45: 24 Waterford Heights | C45: 2110528 | D45: 2 | E45: 9 | F45: Chestermere | G45: Cost | H45: Pre-Sold | I45: Construction | J45: 0.6 | K45: 0.775 | L45: 0.675 | M45: 242500 | N45: 300000 | O45: 242500 | P45: 1060000 | Q45: 863520 | R45: 271.12088 | S45: 5413.3806 | T45: 3185 | U45: 572100 | V45: 179.62323 | W45: 145500 | X45: 394500 | Y45: 540000 | Z45: 0.62534742 | AA45: 0.66290204 | AB45: 336904.5 | AC45: 44645 | AD45: 145500 | AE45: 191404.5 | AF45: 336904.5 | AG45: 0 | AH45: 0 | AI45: 0.645 | AJ45: 0 | AK45: 203095.5 | AL45: 203095.5 | AM45: 336904.5 | AO45: 336904.5 | AP45: 44820 | AQ45: 44831 | AT45: 822400 | AU45: 41120 | AV45: 863520 | AX45: 80500 | AY45: 0.093223087 | AZ45: Balwinder Malhi | BA45: 0.81464151 | BB45: 44294
B46: 89 Waterford Road | C46: 2110528 | D46: 2 | E46: 25 | F46: Chestermere | G46: Cost | H46: Pre-Sold | I46: Construction | J46: 0.6 | K46: 0.775 | L46: 0.675 | M46: 223100 | N46: 300000 | O46: 223100 | P46: 950000 | Q46: 889899.99 | R46: 313.8977 | S46: 4980.026 | T46: 2835 | U46: 503400 | V46: 177.56614 | W46: 133860 | X46: 429177.5 | Y46: 563037.5 | Z46: 0.6326975 | AA46: 0.775 | AB46: 510180.5 | AC46: 44645 | AD46: 133860 | AE46: 353283 | AF46: 487143 | AG46: 0 | AH46: 23037.5 | AI46: 0.895 | AJ46: 0 | AK46: 52857 | AL46: 75894.5 | AM46: 487143 | AO46: 487143 | AP46: 44820 | AQ46: 44840 | AR46: 44865 | AT46: 847523.8 | AU46: 42376.19 | AV46: 889899.99 | AX46: 90000 | AY46: 0.10113496 | AZ46: Jaswinder Mann & Jaspal Kaur Mann | BA46: 0.93673683 | BB46: 44322
B47: 20 Waterford Heights | C47: 2110528 | D47: 2 | E47: 10 | F47: Chestermere | G47: Cost | H47: Pre-Sold | I47: Construction | J47: 0.6 | K47: 0.775 | L47: 0.675 | M47: 223100 | N47: 300000 | O47: 223100 | P47: 1070000 | Q47: 976002.3 | R47: 309.6454 | S47: 4980.026 | T47: 3152 | U47: 651100 | V47: 206.56726 | W47: 133860 | X47: 473640 | Y47: 607500 | Z47: 0.62243706 | AA47: 0.69492107 | AB47: 607500 | AC47: 44645 | AD47: 133860 | AE47: 473640 | AF47: 607500 | AG47: 0 | AH47: 0 | AI47: 1 | AJ47: 0 | AK47: 0 | AL47: 0 | AM47: 607500 | AO47: 607500 | AP47: 44949 | AQ47: 44959 | AR47: 44991 | AT47: 929526 | AU47: 46476.3 | AV47: 976002.3 | AX47: 120427.5 | AY47: 0.12338854 | AZ47: Murtatha Al-Saiedy | BA47: 0.91215168 | BB47: 44397
B48: 82 Waterford Road | C48: 2110528 | D48: 6 | E48: 21 | F48: Chestermere | G48: Cost | H48: Pre-Sold | I48: Construction | J48: 0.6 | K48: 0.775 | L48: 0.675 | M48: 191250 | N48: 300000 | O48: 191250 | P48: 785000 | Q48: 700000 | R48: 291.54519 | S48: 5184.5401 | T48: 2401 | U48: 423100 | V48: 176.21824 | W48: 114750 | X48: 357750 | Y48: 472500 | Z48: 0.675 | AA48: 0.76910556 | AB48: 375187 | AC48: 44645 | AD48: 114750 | AE48: 260437 | AF48: 375187 | AG48: 0 | AH48: 0 | AI48: 0.77 | AJ48: 0 | AK48: 97313 | AL48: 97313 | AM48: 375187 | AO48: 375187 | AP48: 44949 | AQ48: 44960 | AT48: 666666.67 | AU48: 33333.333 | AV48: 700000 | AX48: 69000 | AY48: 0.098571429 | AZ48: Ajminder Kaur | BA48: 0.89171975 | BB48: 44481
B49: 125 Spear Grass Close, Carseland | C49: 0711421 | D49: 10 | E49: 7 | F49: Rural Alberta | G49: Cost | H49: Pre-Sold | I49: Construction | J49: 0.5 | K49: 0.725 | L49: 0.625 | M49: 85000 | N49: 85000 | O49: 85000 | P49: 605000 | Q49: 605000 | R49: 344.72934 | S49: 9314 | T49: 1755 | U49: 491900 | V49: 280.2849 | W49: 42500 | X49: 332500 | Y49: 375000 | Z49: 0.61983471 | AA49: 0.650026 | AB49: 345486 | AC49: 44470 | AD49: 42500 | AE49: 302986 | AF49: 345486 | AG49: 0 | AH49: 0 | AI49: 0.94 | AJ49: 0 | AK49: 29514 | AL49: 29514 | AM49: 345486 | AO49: 345486 | AP49: 44973 | AQ49: 44980 | AR49: 45014 | AT49: 576200 | AU49: 28810 | AV49: 605010 | AW49: 46616.88 | AX49: 60501 | AY49: 0.1 | AZ49: Bonnie & Roy Klatzel | BA49: 1.0000165 | BB49: 44266
B50: 16 Waterford Heights | C50: 2110528 | D50: 2 | E50: 11 | F50: Chestermere | G50: Cost | H50: Pre-Sold | I50: Construction | J50: 0.6 | K50: 0.775 | L50: 0.675 | M50: 223100 | N50: 300000 | O50: 223100 | P50: 1050000 | Q50: 952776.25 | R50: 313.10426 | S50: 4980.026 | T50: 3043 | U50: 652100 | V50: 214.2951 | W50: 133860 | X50: 473640 | Y50: 607500 | Z50: 0.63761035 | AA50: 0.69412706 | AB50: 574895 | AC50: 44645 | AD50: 133860 | AE50: 441035 | AF50: 574895 | AG50: 0 | AH50: 0 | AI50: 0.95 | AJ50: 0 | AK50: 32605 | AL50: 32605 | AM50: 574895 | AO50: 574895 | AP50: 44985 | AQ50: 44986 | AR50: 45019 | AT50: 907405.95 | AU50: 45370.298 | AV50: 952776.25 | AX50: 100000 | AY50: 0.10495644 | AZ50: Tamer Hammoud and Lamia Akl | BA50: 0.90740595 | BB50: 44546
B51: 36 Waterford Heights | C51: 2110528 | D51: 2 | E51: 6 | F51: Chestermere | G51: Cost | H51: Pre-Sold | I51: Construction | J51: 0.6 | K51: 0.775 | L51: 0.675 | M51: 239900 | N51: 250000 | O51: 239900 | P51: 860000 | Q51: 849999.99 | R51: 276.3329 | S51: 5413 | T51: 3076 | U51: 435000 | V51: 141.41743 | W51: 143940 | X51: 379107.5 | Y51: 523047.5 | Z51: 0.61535001 | AA51: 0.775 | AB51: 496947.5 | AC51: 44582 | AD51: 143940 | AE51: 353007.5 | AF51: 496947.5 | AG51: 0 | AH51: 0 | AI51: 0.94 | AJ51: 0 | AK51: 26100 | AL51: 26100 | AM51: 496947.5 | AO51: 496947.5 | AP51: 45022 | AQ51: 45029 | AT51: 809523.8 | AU51: 40476.19 | AV51: 849999.99 | AX51: 85000 | AY51: 0.1 | AZ51: Harpritt Sohi & Mandip Sohi | BA51: 0.98837208 | BB51: 44168
B52: 57 Waterford Road | C52: 2110528 | D52: 2 | E52: 17 | F52: Chestermere | G52: Cost | H52: Pre-Sold | I52: Construction | J52: 0.6 | K52: 0.775 | L52: 0.675 | M52: 218250 | N52: 300000 | O52: 218250 | P52: 990000 | Q52: 968210.25 | R52: 307.07588 | S52: 4886.8106 | T52: 3153 | U52: 537600 | V52: 170.50428 | W52: 130950 | X52: 454833.75 | Y52: 585783.75 | Z52: 0.60501709 | AA52: 0.775 | AB52: 545463.75 | AC52: 44645 | AD52: 130950 | AE52: 414513.75 | AF52: 545463.75 | AG52: 0 | AH52: 0 | AI52: 0.925 | AJ52: 0 | AK52: 40320 | AL52: 40320 | AM52: 545463.75 | AO52: 545463.75 | AP52: 45063 | AQ52: 45089 | AR52: 45117 | AT52: 922105 | AU52: 46105.25 | AV52: 968210.25 | AX52: 80410.51 | AY52: 0.08305067 | AZ52: Aftab Shah & Urooj Sheikh | BA52: 0.97799015 | BB52: 44506
B53: 65 Waterford Road | C53: 2110528 | D53: 2 | E53: 19 | F53: Chestermere | G53: Cost | H53: Pre-Sold | I53: Construction | J53: 0.6 | K53: 0.775 | L53: 0.675 | M53: 215910 | N53: 300000 | O53: 215910 | P53: 990000 | Q53: 940825.2 | R53: 296.41626 | S53: 4898.328 | T53: 3174 | U53: 531600 | V53: 167.48582 | W53: 129546 | X53: 449774.25 | Y53: 579320.25 | Z53: 0.61575758 | AA53: 0.775 | AB53: 579320.25 | AC53: 44645 | AD53: 129546 | AE53: 449774.25 | AF53: 579320.25 | AG53: 0 | AH53: 0 | AI53: 1 | AJ53: 0 | AK53: 0 | AL53: 0 | AM53: 579320.25 | AO53: 579320.25 | AP53: 45089 | AQ53: 45096 | AR53: 45131 | AT53: 896024 | AU53: 44801.2 | AV53: 940825.2 | AX53: 185000 | AY53: 0.19663589 | AZ53: Kulwant Nijjar and Manjit Nijjar | BA53: 0.95032848 | BB53: 44507
B54: 33 Waterford Terrace, Chestermere | C54: 2210618 | D54: 2 | E54: 31 | F54: Chestermere | G54: Cost | H54: Pre-Sold | I54: Construction | J54: 0.6 | K54: 0.775 | L54: 0.675 | M54: 245000 | N54: 300000 | O54: 245000 | P54: 915000 | Q54: 906885 | R54: 322.73488 | S54: 4886.8106 | T54: 2810 | U54: 507600 | V54: 180.64057 | W54: 147000 | X54: 436265 | Y54: 583265 | Z54: 0.64315211 | AA54: 0.775 | AB54: 532505 | AC54: 44886 | AD54: 147000 | AE54: 385505 | AF54: 532505 | AG54: 0 | AH54: 0 | AI54: 0.9 | AJ54: 0 | AK54: 50760 | AL54: 50760 | AM54: 532505 | AO54: 532505 | AP54: 45097 | AQ54: 45103 | AR54: 45131 | AT54: 863700 | AU54: 43185 | AV54: 906885 | AX54: 45350 | AY54: 0.05000634 | AZ54: Ravinder Pelia & Kirandeep Khasria | BA54: 0.99113115 | BB54: 44511 | BC54: Received mortgage financing pre-approval letter from RBC for borrower dated October 10, 2022
B55: 168 Sandpiper Landing, Chestermere | C55: 2012107 | D55: 8 | E55: 9 | F55: Chestermere | G55: Cost | H55: Pre-Sold | I55: Construction | J55: 0.6 | K55: 0.775 | L55: 0.675 | M55: 232900 | N55: 275000 | O55: 232900 | P55: 900000 | Q55: 895156.5 | R55: 358.34928 | S55: 5620.9086 | T55: 2498 | U55: 509900 | V55: 204.1233 | W55: 139740 | X55: 435930 | Y55: 575670 | Z55: 0.64309425 | AA55: 0.775 | AB55: 463492 | AC55: 44939 | AD55: 139740 | AE55: 323752 | AF55: 463492 | AG55: 0 | AH55: 0 | AI55: 0.78 | AJ55: 0 | AK55: 112178 | AL55: 112178 | AM55: 463492 | AO55: 463492 | AP55: 45098 | AQ55: 45107 | AR55: 45131 | AT55: 852530 | AU55: 42626.5 | AV55: 895156.5 | AX55: 88547.66 | AY55: 0.098918636 | AZ55: Narinder Singh & Satwant Kaur | BA55: 0.99461833 | BB55: 44553
B56: 41 Waterford Terrace, Chestermere | C56: 2210618 | D56: 2 | E56: 33 | F56: Chestermere | G56: Cost | H56: Pre-Sold | I56: Construction | J56: 0.6 | K56: 0.775 | L56: 0.675 | M56: 272000 | N56: 300000 | O56: 272000 | P56: 960000 | Q56: 954975 | R56: 303.93857 | S56: 5413.1653 | T56: 3142 | U56: 540600 | V56: 172.05602 | W56: 163200 | X56: 444300 | Y56: 607500 | Z56: 0.63614231 | AA56: 0.7476003 | AB56: 580470 | AC56: 44886 | AD56: 163200 | AE56: 417270 | AF56: 580470 | AG56: 0 | AH56: 0 | AI56: 0.95 | AJ56: 0 | AK56: 27030 | AL56: 27030 | AM56: 580470 | AO56: 580470 | AP56: 45099 | AQ56: 45113 | AR56: 45147 | AT56: 909500 | AU56: 45475 | AV56: 954975 | AX56: 89412.49 | AY56: 0.093628095 | AZ56: Simranjit Singh Sidhu | BA56: 0.99476562 | BB56: 44511
B57: 72 Waterford Terrace, Chestermere | C57: 2210618 | D57: 7 | E57: 14 | F57: Chestermere | G57: Cost | H57: Pre-Sold | I57: Construction | J57: 0.6 | K57: 0.775 | L57: 0.675 | M57: 248000 | N57: 275000 | O57: 248000 | P57: 915000 | Q57: 908145 | R57: 319.54433 | S57: 5872.7838 | T57: 2842 | U57: 517100 | V57: 181.94933 | W57: 148800 | X57: 444152.5 | Y57: 592952.5 | Z57: 0.65292712 | AA57: 0.775 | AB57: 567097.5 | AC57: 44886 | AD57: 148800 | AE57: 418297.5 | AF57: 567097.5 | AG57: 0 | AH57: 0 | AI57: 0.95 | AJ57: 0 | AK57: 25855 | AL57: 25855 | AM57: 567097.5 | AO57: 567097.5 | AP57: 45131 | AQ57: 45135 | AR57: 45163 | AT57: 864900 | AU57: 43245 | AV57: 908145 | AX57: 95380 | AY57: 0.10502728 | AZ57: Gagandeep Kaur Mann | BA57: 0.9925082 | BB57: 44511
B58: 32 Vantage Drive, Cochrane | C58: 2211425 | D58: 6 | E58: 8 | F58: Cochrane | G58: Cost | H58: Speculative | I58: Construction | J58: 0.5 | K58: 0.725 | L58: 0.625 | M58: 155000 | N58: 250000 | O58: 155000 | P58: 685000 | Q58: 685000 | R58: 301.36384 | S58: 3942 | T58: 2273 | U58: 399400 | V58: 175.71491 | W58: 77500 | X58: 324440 | Y58: 401940 | Z58: 0.58677372 | AA58: 0.725 | AB58: 385964 | AC58: 44991 | AD58: 77500 | AE58: 308464 | AF58: 385964 | AG58: 0 | AH58: 0 | AI58: 0.96 | AJ58: 0 | AK58: 15976 | AL58: 15976 | AM58: 385964 | AO58: 385964 | AP58: 45251 | AQ58: 45258 | AR58: 45282 | AT58: 687619.05 | AU58: 34380.952 | AV58: 722000 | AX58: 30000 | AY58: 0.041551247 | AZ58: Jonah Gilham and Zoe Stein | BA58: 1.0540146 | BB58: 45223
B59: 73 North Bridges Bay, Langdon | C59: 2011558 | D59: 1 | E59: 29 | F59: Langdon | G59: Cost | H59: Pre-Sold | I59: Construction | J59: 0.6 | K59: 0.775 | L59: 0.675 | M59: 184000 | N59: 215000 | O59: 184000 | P59: 840000 | Q59: 840000 | R59: 266.41294 | S59: 8859 | T59: 3153 | U59: 548600 | V59: 173.99302 | W59: 110400 | X59: 456600 | Y59: 567000 | Z59: 0.675 | AA59: 0.77395577 | AB59: 545056 | AC59: 44981 | AD59: 110400 | AE59: 434656 | AF59: 545056 | AG59: 0 | AH59: 0 | AI59: 0.96 | AJ59: 0 | AK59: 21944 | AL59: 21944 | AM59: 545056 | AO59: 545056 | AP59: 45254 | AQ59: 45261 | AR59: 45282 | AT59: 944450 | AU59: 47222.5 | AV59: 991672.5 | AX59: 89445 | AY59: 0.090196108 | AZ59: Chris Brown & Kimberly McLellan | BA59: 1.1805625 | BB59: 44674
B60: < Insert Rows Above > | AF60: =SUM(AF4:AF59) -> 22646837 | AM60: =SUM(AM4:AM59) -> 22646837

Sheet Land Comps
B2: Plan | C2: Block | D2: Lot | E2: Civic Address - If Known | F2: Sale Price | G2: Sale Date | H2: Square Meters | I2: Square feet | J2: $ per sq. ft. | K2: Frontage (M) | L2: Depth(M) | M2: Frotage (F) | N2: Depth(F) | O2: Cost per ff
B3: # | C3: # | D3: # | F3: $ | G3: date | H3: m2 | I3: sq. ft. | K3: metres | L3: metres | M3: feet | N3: feet
B4: 2412602 | C4: 11 | D4: 41 | E4: 111 Belvedere Cresecent | F4: 205000 | G4: 45782 | K4: 8.92 | M4: =K4*3.28084 -> 29.265093 | O4: =F4/M4 -> 7004.9325
B5: 2412602 | C5: 11 | D5: 45 | E5: 91 Belvedere Cresecent | F5: 205000 | G5: 45889 | K5: 8.92 | M5: =K5*3.28084 -> 29.265093 | O5: =F5/M5 -> 7004.9325
B6: 2412602 | C6: 11 | D6: 46 | E6: 87 Belvedere Cresecent | F6: 205000 | G6: 45711 | K6: 8.92 | M6: =K6*3.28084 -> 29.265093 | O6: =F6/M6 -> 7004.9325
B7: 2412602 | C7: 11 | D7: 48 | E7: 79 Belvedere Cresecent | F7: 205000 | G7: 45889 | K7: 8.92 | M7: =K7*3.28084 -> 29.265093 | O7: =F7/M7 -> 7004.9325
B8: 2412602 | C8: 11 | D8: 49 | E8: 75 Belvedere Cresecent | F8: 205000 | G8: 45874 | K8: 8.92 | M8: =K8*3.28084 -> 29.265093 | O8: =F8/M8 -> 7004.9325
B9: 2412602 | C9: 11 | D9: 50 | E9: 71 Belvedere Cresecent | F9: 205000 | G9: 45782 | K9: 8.92 | M9: =K9*3.28084 -> 29.265093 | O9: =F9/M9 -> 7004.9325
A10: CCH Lot | B10: 2412602 | C10: 11 | D10: 32 | E10: 151 Belvedere Cresecent | F10: 205000 | G10: 45773 | K10: 8.92 | M10: =K10*3.28084 -> 29.265093 | O10: =F10/M10 -> 7004.9325
A11: CCH Lot | B11: 2412602 | C11: 11 | D11: 33 | E11: 147 Belvedere Cresecent | F11: 205000 | G11: 45852 | K11: 8.92 | M11: =K11*3.28084 -> 29.265093 | O11: =F11/M11 -> 7004.9325
B12: 2412602 | C12: 11 | D12: 17 | E12: 211 Belvedere Cresecent | F12: 180000 | G12: 45749 | K12: 7.72 | M12: =K12*3.28084 -> 25.328085 | O12: =F12/M12 -> 7106.7355
A13: CCH Lot | B13: 2412602 | C13: 11 | D13: 18 | E13: 207 Belvedere Cresecent | F13: 180000 | G13: 45773 | K13: 7.72 | M13: =K13*3.28084 -> 25.328085 | O13: =F13/M13 -> 7106.7355
B14: 2412602 | C14: 11 | D14: 19 | E14: 203 Belvedere Cresecent | F14: 180000 | G14: 45749 | K14: 7.72 | M14: =K14*3.28084 -> 25.328085 | O14: =F14/M14 -> 7106.7355
B16: Average | F16: =AVERAGEIF(F4:F15,">0") -> 198181.82 | H16: =AVERAGEIF(H4:H15,">0") -> #DIV/0! | I16: =AVERAGEIF(I4:I15,">0") -> #DIV/0! | J16: =AVERAGEIF(J4:J15,">0") -> #DIV/0! | M16: =M9 -> 29.265093 | O16: =AVERAGE(O4:O15) -> 7032.697
B18: 2412602 | C18: 11 | D18: 39 | E18: 119 Belvedere Cresecent | F18: =Summary!D24 -> 240000 | G18: ?? | H18: 315 | I18: =H18*10.76 -> 3389.4 | J18: =F18/I18 -> 70.808993
D21: $ Per FF | E21: Implied Value
B22: Min | D22: =MIN(O4:O15) -> 7004.9325 | E22: =D22*$M$4 -> 205000
B23: 25th Percentile | D23: =_xlfn.PERCENTILE.INC(O4:O15,0.25) -> 7004.9325 | E23: =D23*$M$4 -> 205000
B24: Median | D24: =O16 -> 7032.697 | E24: =D24*$M$4 -> 205812.53
B25: 75th Percentile | D25: =_xlfn.PERCENTILE.INC(O4:O15,0.75) -> 7055.834 | E25: =D25*$M$4 -> 206489.64
B26: Max | D26: =MAX(O4:O15) -> 7106.7355 | E26: =D26*$M$4 -> 207979.27
B28: Subject Property | F28: 432.34658 | G28: 1264613.8
B30: Sample Variance | F30: =_xlfn.STDEV.S(J8:J15) -> #DIV/0!
B32: KV FF | D32: 7000 | F32: =M16 -> 29.265093
B33: KV Internal Value | D33: =D32*M18 -> 0 | F33: =D32*F32 -> 204855.65
